Workbook

Sheet INTERVIEWS SUMMARY
C1: CORE CUSTOMER PAINS, NEEDS, GAINS - INTERVIEWS SUMMARY | K1: Z
C4: Interviewer (team member) name | D4: Interviewee name | E4: Profile (Target Segment Fit) | F4: Key Challenges (Pains) | G4: Motivations/Goals (Needs) | H4: Desired outcomes from a specific product/service (Gains) | I4: Actions Taken (Past Behaviors) | J4: Unexpected Insights | K4: Direct Quotes
E5: YES | F5: Limited office space (3 small offices in GB) | G5: Serviced office with amenities and community | H5: Access to flexible, well-designed workspaces (e.g., Workshop 17) | I5: Cross-marketing deal with Workshop 17 for free access | J5: Workshop 17 operates at >100% occupancy by overbooking seats | K5: "W17 staff calls all clients by their first name."
E6: YES | F6: Small coffee shop nearby | G6: Proximity to food/beverage services | H6: Coffee delivery to workspace (e.g., Kumba Coffee) | I6: Partnered with Kumba Coffee for desk deliveries | J6: Kumba Coffee expands to multiple locations (Telfair, Vacoas, Mont Choisy)
E7: YES | F7: Isolation in a private office | G7: Companionship and community interaction | H7: Networking and collaboration opportunities | I7: Moved to co-working spaces (Workshop 17) | J7: Ennoia gained new members via W17’s expat-centric community | K7: "If I rented a small office, I’d be lonely."
E8: YES | F8: Need for meeting rooms (weekly client meetings) | G8: Professional, well-decorated meeting spaces | H8: Easy booking of meeting rooms via app | I8: Booked W17 meeting rooms online | J8: W17’s meeting rooms enhance client interactions
E9: YES | F9: Lack of transparency in pricing/lease terms | G9: Flexible lease terms and cost clarity | H9: Reduced operational costs and scalable workspace | I9: Worked with real estate brokers to avoid hidden costs | J9: Co-working spaces become expensive as businesses grow | K9: "Negotiating lease terms takes too long and feels one-sided."
E10: YES | F10: Limited privacy in shared spaces | G10: Secure, private workspace | H10: Confidential meetings and focused work | I10: Considered moving to a larger office | J10: W17 offers secure access (badge/Face ID) and cameras | K10: "The biggest challenge is not having enough privacy in co-working spaces."
E11: YES | F11: Low brand visibility in current setup | G11: Professional environment for branding | H11: Enhanced company image and client attraction | I11: Explored locations for better corporate branding | J11: W17’s aesthetic and events (yoga, workshops) boost visibility
E12: YES | F12: Work-life balance challenges | G12: Separation of home/work | H12: Improved productivity and well-being | I12: Initially used home-office setup | J12: W17 offers wellness amenities (showers, green spaces) | K12: "I need separation between home and work."
E13: YES | F13: Commuting and accessibility issues | G13: Accessible location with parking | H13: Short commute and employee convenience | I13: Benchmarked competitor office environments | J13: Sustainability (green spaces) and parking are critical for employee retention | K13: "Environment and well-being matter more than higher pay for some staff."
E14: YES | F14: High operational costs (e.g., fit-outs, utilities) | G14: Plug-and-play office setup | H14: Immediate move-in readiness and reduced setup hassles | I14: Avoided fit-outs by choosing pre-fitted spaces | J14: W17 offers car wash services and concierge-like conveniences
E15: YES | F15: Overpriced co-working spaces for scaling businesses | G15: Affordable scalability | H15: Cost-effective expansion (e.g., Rs 60,000 for 200m² in Quatre Bornes rejected as too costly) | I15: Tried co-working spaces but shifted due to rising costs | J15: W17’s flexible seating allows scaling without long-term commitments | K15: "Co-working spaces became too expensive as my business grew."
E16: YES | F16: Poor connectivity and IT infrastructure | G16: Strong IT infrastructure and modern amenities | H16: Reliable internet and professional tools for productivity | I16: Prioritized locations with fast internet and printing services | J16: W17’s expat-centric community offers networking opportunities | K16: "A workspace with strong IT infrastructure is non-negotiable."
E17: YES | F17: Limited amenities nearby | G17: Proximity to shopping malls/services | H17: Convenience for employees and clients | I17: Chose locations near malls (e.g., Telfair, Precinct) | J17: Mix-use facilities (e.g., W17’s amphitheater for events) drive engagement
E18: YES | F18: Inflexible operating hours | G18: Tailored operating hours | H18: Improved work-life balance for employees | I18: Sought locations with 24/7 access (e.g., W17’s badge system) | J18: W17’s ambiance adapts to moods (bright/shady areas) | K18: "I’d pay more for a workspace that offers 24/7 access and privacy."
E19: YES | F19: Difficulty finding spaces compliant with global sustainability standards (e.g., LEED) | G19: Align with corporate ESG goals | H19: Reduced carbon footprint and enhanced brand reputation | I19: Leased older buildings and retrofitted them with green technology | J19: Tenants prioritize eco-certifications even if costs are 10-15% higher | K19: “We need a building that reflects our commitment to sustainability—it’s non-negotiable.”
E20: YES | F20: Lack of advanced tech infrastructure (e.g., IoT, smart building systems) | G20: Future-proof workspaces | H20: Access to smart HVAC, lighting, and occupancy sensors | I20: Partnered with third-party tech vendors to upgrade office systems | J20: Buildings with tech integration attract tech-forward tenants
E21: YES | F21: Inflexible lease terms for scaling (no expansion clauses) | G21: Dynamic space adjustments | H21: Ability to add/remove space without penalties | I21: Negotiated lease addendums for expansion rights | J21: Tenants value “growth-friendly” leases over short-term discounts | K21: “We left our last office because the landlord since it was difficult to expand.”
E22: YES | F22: Limited EV charging stations | G22: Support green commuting | H22: Reduced employee carbon footprint | I22: Installed private EV chargers at previous office | J22: Buildings with EV infrastructure see higher tenant retention | K22: “Our employees/our policy requires EV charging”
E23: YES | F23: Poor post-pandemic health safeguards (e.g., air quality) | G23: Employee health and safety | H23: Advanced air filtration and touchless systems | I23: Conducted independent air quality audits | J23: Tenants pay premiums for health-certified buildings (e.g., WELL Certification) | K23: “After COVID, air quality is as important as rent costs.”
E24: YES | F24: No access to tenant networking communities | G24: Collaboration opportunities | H24: Partnerships with adjacent businesses | I24: Hosted informal mixers with other tenants | J24: Buildings with curated tenant networks see higher satisfaction | K24: “Isolation in a premium tower defeats the purpose of Grade A.”
E25: YES | F25: Limited cultural/recreational spaces (e.g., rooftop lounges) | G25: Employee well-being | H25: On-site cafes, event spaces, and relaxation zones | I25: Subsidized off-site gym memberships | J25: Recreational amenities reduce employee turnover | K25: “example, a common break out area isn’t a luxury—it’s a productivity tool.”
E26: YES | F26: No bundled services (cleaning, utilities) | G26: Simplified cost management | H26: All-inclusive pricing with no hidden fees | I26: Outsourced facility management to third parties | J26: Tenants prefer bundled services even at a premium | K26: “Managing different suppliers is a nightmare.”

Sheet PAINS - PRIORITIZATION MATRIX
C1: CUSTOMER PAINS PRIORITIZATION MATRIX
C4: CUSTOMER PAINS | D4: [01] | E4: Severity (1-5) | F4: [02] | G4: Frequency (1-5) | H4: [03] | I4: Impact (1-5) | J4: RANKING
C5: ='INTERVIEWS SUMMARY'!F5 -> Limited office space (3 small offices in GB) | D5: → | E5: 4 | F5: → | G5: 1 | H5: → | I5: 1 | J5: =E5*2+G5+I5*3 -> 12
C6: ='INTERVIEWS SUMMARY'!F6 -> Small coffee shop nearby | D6: → | E6: 3 | F6: → | G6: 4 | H6: → | I6: 4 | J6: =E6*2+G6+I6*3 -> 22
C7: ='INTERVIEWS SUMMARY'!F7 -> Isolation in a private office | D7: → | E7: 4 | F7: → | G7: 5 | H7: → | I7: 4 | J7: =E7*2+G7+I7*3 -> 25
C8: ='INTERVIEWS SUMMARY'!F8 -> Need for meeting rooms (weekly client meetings) | D8: → | E8: 5 | F8: → | G8: 3 | H8: → | I8: 5 | J8: =E8*2+G8+I8*3 -> 28
C9: ='INTERVIEWS SUMMARY'!F9 -> Lack of transparency in pricing/lease terms | D9: → | E9: 5 | F9: → | G9: 2 | H9: → | I9: 5 | J9: =E9*2+G9+I9*3 -> 27
C10: ='INTERVIEWS SUMMARY'!F10 -> Limited privacy in shared spaces | D10: → | E10: 4 | F10: → | G10: 5 | H10: → | I10: 4 | J10: =E10*2+G10+I10*3 -> 25
C11: ='INTERVIEWS SUMMARY'!F11 -> Low brand visibility in current setup | D11: → | E11: 3 | F11: → | G11: 2 | H11: → | I11: 3 | J11: =E11*2+G11+I11*3 -> 17
C12: ='INTERVIEWS SUMMARY'!F12 -> Work-life balance challenges | D12: → | E12: 5 | F12: → | G12: 5 | H12: → | I12: 5 | J12: =E12*2+G12+I12*3 -> 30
C13: ='INTERVIEWS SUMMARY'!F13 -> Commuting and accessibility issues | D13: → | E13: 4 | F13: → | G13: 5 | H13: → | I13: 4 | J13: =E13*2+G13+I13*3 -> 25
C14: ='INTERVIEWS SUMMARY'!F14 -> High operational costs (e.g., fit-outs, utilities) | D14: → | E14: 5 | F14: → | G14: 5 | H14: → | I14: 5 | J14: =E14*2+G14+I14*3 -> 30
C15: ='INTERVIEWS SUMMARY'!F15 -> Overpriced co-working spaces for scaling businesses | D15: → | E15: 4 | F15: → | G15: 3 | H15: → | I15: 4 | J15: =E15*2+G15+I15*3 -> 23
C16: ='INTERVIEWS SUMMARY'!F16 -> Poor connectivity and IT infrastructure | D16: → | E16: 5 | F16: → | G16: 5 | H16: → | I16: 5 | J16: =E16*2+G16+I16*3 -> 30
... C26: ='INTERVIEWS SUMMARY'!F26 -> No bundled services (cleaning, utilities) | D26: → | E26: 3 | F26: → | G26: 4 | H26: → | I26: 3 | J26: =E26*2+G26+I26*3 -> 19

Sheet NEEDS - PRIORITIZATION MATRIX
C1: CUSTOMER NEEDS PRIORITIZATION MATRIX
C4: CUSTOMER NEEDS | D4: [01] | E4: Severity (1-5) | F4: [02] | G4: Frequency (1-5) | H4: [03] | I4: Impact (1-5) | J4: RANKING
C5: ='INTERVIEWS SUMMARY'!G5 -> Serviced office with amenities and community | D5: → | E5: 5 | F5: → | G5: 5 | H5: → | I5: 5 | J5: =E5*2+G5+I5*3 -> 30
C6: ='INTERVIEWS SUMMARY'!G6 -> Proximity to food/beverage services | D6: → | E6: 3 | F6: → | G6: 4 | H6: → | I6: 4 | J6: =E6*2+G6+I6*3 -> 22
C7: ='INTERVIEWS SUMMARY'!G7 -> Companionship and community interaction | D7: → | E7: 4 | F7: → | G7: 5 | H7: → | I7: 4 | J7: =E7*2+G7+I7*3 -> 25
C8: ='INTERVIEWS SUMMARY'!G8 -> Professional, well-decorated meeting spaces | D8: → | E8: 5 | F8: → | G8: 3 | H8: → | I8: 5 | J8: =E8*2+G8+I8*3 -> 28
C9: ='INTERVIEWS SUMMARY'!G9 -> Flexible lease terms and cost clarity | D9: → | E9: 5 | F9: → | G9: 2 | H9: → | I9: 5 | J9: =E9*2+G9+I9*3 -> 27
C10: ='INTERVIEWS SUMMARY'!G10 -> Secure, private workspace | D10: → | E10: 4 | F10: → | G10: 5 | H10: → | I10: 4 | J10: =E10*2+G10+I10*3 -> 25
C11: ='INTERVIEWS SUMMARY'!G11 -> Professional environment for branding | D11: → | E11: 3 | F11: → | G11: 2 | H11: → | I11: 3 | J11: =E11*2+G11+I11*3 -> 17
C12: ='INTERVIEWS SUMMARY'!G12 -> Separation of home/work | D12: → | E12: 5 | F12: → | G12: 5 | H12: → | I12: 5 | J12: =E12*2+G12+I12*3 -> 30
C13: ='INTERVIEWS SUMMARY'!G13 -> Accessible location with parking | D13: → | E13: 4 | F13: → | G13: 5 | H13: → | I13: 4 | J13: =E13*2+G13+I13*3 -> 25
C14: ='INTERVIEWS SUMMARY'!G14 -> Plug-and-play office setup | D14: → | E14: 5 | F14: → | G14: 1 | H14: → | I14: 5 | J14: =E14*2+G14+I14*3 -> 26
C15: ='INTERVIEWS SUMMARY'!G15 -> Affordable scalability | D15: → | E15: 5 | F15: → | G15: 5 | H15: → | I15: 5 | J15: =E15*2+G15+I15*3 -> 30
C16: ='INTERVIEWS SUMMARY'!G16 -> Strong IT infrastructure and modern amenities | D16: → | E16: 5 | F16: → | G16: 5 | H16: → | I16: 5 | J16: =E16*2+G16+I16*3 -> 30
... C24: ='INTERVIEWS SUMMARY'!G24 -> Collaboration opportunities | D24: → | E24: 3 | F24: → | G24: 3 | H24: → | I24: 3 | J24: =E24*2+G24+I24*3 -> 18

Sheet GAINS - PRIORITIZATION MATRIX
C1: CUSTOMER GAINS PRIORITIZATION MATRIX
C4: CUSTOMER GAINS | D4: [01] | E4: Severity (1-5) | F4: [02] | G4: Frequency (1-5) | H4: [03] | I4: Impact (1-5) | J4: RANKING
C5: Improved productivity and well-being | D5: → | E5: 5 | F5: → | G5: 5 | H5: → | I5: 5 | J5: =E5*2+G5+I5*3 -> 30
C6: Reliable internet and professional tools | D6: → | E6: 5 | F6: → | G6: 5 | H6: → | I6: 5 | J6: =E6*2+G6+I6*3 -> 30
C7: Reduced operational costs and scalability | D7: → | E7: 5 | F7: → | G7: 5 | H7: → | I7: 5 | J7: =E7*2+G7+I7*3 -> 30
C8: Confidential meetings and focused work | D8: → | E8: 5 | F8: → | G8: 5 | H8: → | I8: 5 | J8: =E8*2+G8+I8*3 -> 30
C9: Improved work-life balance | D9: → | E9: 5 | F9: → | G9: 5 | H9: → | I9: 5 | J9: =E9*2+G9+I9*3 -> 30
C10: Advanced air filtration and touchless systems | D10: → | E10: 5 | F10: → | G10: 5 | H10: → | I10: 5 | J10: =E10*2+G10+I10*3 -> 30
C11: All-inclusive pricing with no hidden fees | D11: → | E11: 5 | F11: → | G11: 5 | H11: → | I11: 5 | J11: =E11*2+G11+I11*3 -> 30
C12: Access to flexible, well-designed workspaces | D12: → | E12: 5 | F12: → | G12: 5 | H12: → | I12: 5 | J12: =E12*2+G12+I12*3 -> 30
C13: Easy booking of meeting rooms via app | D13: → | E13: 5 | F13: → | G13: 5 | H13: → | I13: 5 | J13: =E13*2+G13+I13*3 -> 30
C14: Immediate move-in readiness | D14: → | E14: 5 | F14: → | G14: 3 | H14: → | I14: 5 | J14: =E14*2+G14+I14*3 -> 28
C15: Ability to add/remove space without penalties | D15: → | E15: 5 | F15: → | G15: 4 | H15: → | I15: 5 | J15: =E15*2+G15+I15*3 -> 29
C16: Cost-effective expansion | D16: → | E16: 5 | F16: → | G16: 4 | H16: → | I16: 5 | J16: =E16*2+G16+I16*3 -> 29
... C24: Coffee delivery to workspace | D24: → | E24: 3 | F24: → | G24: 4 | H24: → | I24: 3 | J24: =E24*2+G24+I24*3 -> 19
C25: Partnerships with adjacent businesses | E25: 3 | G25: 3 | I25: 3 | J25: =E25*2+G25+I25*3 -> 18
C26: Reduced employee carbon footprint | E26: 3 | G26: 3 | I26: 3 | J26: =E26*2+G26+I26*3 -> 18

Sheet PAINS, NEEDS, GAINS SUMMARY
C1: CORE CUSTOMER PAINS, NEEDS, GAINS SUMMARY
C4: [01] | D4: Core customer description
C5: → | D5: MaxCity, a property developer specializing in Grade A office spaces, caters to mid-sized to large enterprises, fast-growing startups, and established professional firms (e.g., tech, finance, consulting, legal) with teams of 10–200+ employees. These clients prioritize scalable, premium office solutions that ensure seamless connectivity to transport hubs, amenities, and talent pools, supporting their growth and operational efficiency.
C6: [02] | D6: Top 3 customer PAINS
C7: → | D7: ='PAINS - PRIORITIZATION MATRIX'!C14 -> High operational costs (e.g., fit-outs, utilities)
C8: → | D8: ='PAINS - PRIORITIZATION MATRIX'!C20 -> Lack of advanced tech infrastructure (e.g., IoT, smart building systems)
C9: → | D9: ='PAINS - PRIORITIZATION MATRIX'!C12 -> Work-life balance challenges
C10: [03] | D10: Top 3 customer NEEDS
C11: → | D11: ='NEEDS - PRIORITIZATION MATRIX'!C23 -> Employee health and safety
C12: → | D12: ='NEEDS - PRIORITIZATION MATRIX'!C16 -> Strong IT infrastructure and modern amenities
C13: → | D13: ='NEEDS - PRIORITIZATION MATRIX'!C15 -> Affordable scalability
C14: [04] | D14: Top 3 customer GAINS
C15: → | D15: ='GAINS - PRIORITIZATION MATRIX'!C5 -> Improved productivity and well-being
C16: → | D16: ='GAINS - PRIORITIZATION MATRIX'!C7 -> Reduced operational costs and scalability
C17: → | D17: ='GAINS - PRIORITIZATION MATRIX'!C12 -> Access to flexible, well-designed workspaces
