Workbook

Sheet Market size
C1: MARKET SIZE AND PROFIT POOL ANALYSIS
C3: MARKET SIZE AVAILABLE
C6: WHY Setting targets precedes strategy formulation. Market size and profitability are the only viable context within which the business can set targets and develop strategies. WHAT Determine the size of the market in terms of total size and total profit pool. HOW 1. Define the number of customers who are potential buyers for your product and service. 2. Determine how many products or services they buy per year. 3. Determine the average price they pay per product/ service. 4. The multiplication of the above 3 variables will give you the size of the market. 5. Multiply by your average gross margin %. 6. This will provide you with the overall profit pool in the market. | F6: Total Number of Customers | K6: 132000
F7: Average Spending per Customer | K7: 800000
F8: Average Number of Purchases per Year | K8: 0.016
F9: Gross Profit Margin (%) | K9: 0.2
F12: Market Size | G12: =YEAR(TODAY()) -> 2025 | I12: =K6*K7*K8 -> 1689600000
F14: Profit Pool | G14: =YEAR(TODAY()) -> 2025 | I14: =I12*K9 -> 337920000
H16: Next | I16: Driving Forces Brainstorm

Sheet Market Attractiveness
B1: Optional tool in case you seek geographical expansion
B2: MARKET ATTRACTIVENESS INDEX
B4: Averaged numbers from base country | H4: Country 1 | I4: Country 2 | J4: Country 3 | K4: Country 4 | L4: Country 5 | M4: Country 6 | N4: Country 7 | O4: Country 8 | P4: Country 9 | Q4: Country 10 | T4: The model provides a combination of the market reality and your own assessment of the strategic relevance of the country. It is a good starting point to evaluate alternative directions for expansion
B6: Sales per person - USD | E6: 5 | G6: population "000
B7: profit per person USD | E7: 1
G8: market size adjustment | T8: 1 | U8: Do calculations for one BASE country - sales per person and profit per person - E6 and E7
B9: Size and profitability adjustment | G9: Market size '000 | H9: =H6*H8*$E$6 -> 0 | I9: =I6*I8*$E$6 -> 0 | J9: =J6*J8*$E$6 -> 0 | K9: =K6*K8*$E$6 -> 0 | L9: =L6*L8*$E$6 -> 0 | M9: =M6*M8*$E$6 -> 0 | N9: =N6*N8*$E$6 -> 0 | O9: =O6*O8*$E$6 -> 0 | ... Q9: =Q6*Q8*$E$6 -> 0 | R9: =AVERAGE(H9:Q9) -> 0 | T9: 2 | U9: Choose the counties for which you want to perform the analyses and input population in row 6
G10: average adjustment | H10: =(H9*100%)/$R$9 -> #DIV/0! | I10: =(I9*100%)/$R$9 -> #DIV/0! | J10: =(J9*100%)/$R$9 -> #DIV/0! | K10: =(K9*100%)/$R$9 -> #DIV/0! | L10: =(L9*100%)/$R$9 -> #DIV/0! | M10: =(M9*100%)/$R$9 -> #DIV/0! | N10: =(N9*100%)/$R$9 -> #DIV/0! | O10: =(O9*100%)/$R$9 -> #DIV/0! | ... Q10: =(Q9*100%)/$R$9 -> #DIV/0!
B11: Much better compared to base | E11: 1.5 | G11: market size index (-3 to +3) | H11: =IFERROR(IF(H10<$E$16,"-3",IF(H10<$E$14,"-2",IF(AND(H10>=$E$14,H10<=$E$13),"-1",IF(H10=$E$13,0,IF(AND(H10>$E$13,H10<$E$12),1,IF(AND(H10>$E$12,H10<$E$11),2,IF(H10>$E$11,"3"))))))),"") | I11: =IFERROR(IF(I10<$E$16,"-3",IF(I10<$E$14,"-2",IF(AND(I10>=$E$14,I10<=$E$13),"-1",IF(I10=$E$13,0,IF(AND(I10>$E$13,I10<$E$12),1,IF(AND(I10>$E$12,I10<$E$11),2,IF(I10>$E$11,"3"))))))),"") | J11: =IFERROR(IF(J10<$E$16,"-3",IF(J10<$E$14,"-2",IF(AND(J10>=$E$14,J10<=$E$13),"-1",IF(J10=$E$13,0,IF(AND(J10>$E$13,J10<$E$12),1,IF(AND(J10>$E$12,J10<$E$11),2,IF(J10>$E$11,"3"))))))),"") | K11: =IFERROR(IF(K10<$E$16,"-3",IF(K10<$E$14,"-2",IF(AND(K10>=$E$14,K10<=$E$13),"-1",IF(K10=$E$13,0,IF(AND(K10>$E$13,K10<$E$12),1,IF(AND(K10>$E$12,K10<$E$11),2,IF(K10>$E$11,"3"))))))),"") | L11: =IFERROR(IF(L10<$E$16,"-3",IF(L10<$E$14,"-2",IF(AND(L10>=$E$14,L10<=$E$13),"-1",IF(L10=$E$13,0,IF(AND(L10>$E$13,L10<$E$12),1,IF(AND(L10>$E$12,L10<$E$11),2,IF(L10>$E$11,"3"))))))),"") | M11: =IFERROR(IF(M10<$E$16,"-3",IF(M10<$E$14,"-2",IF(AND(M10>=$E$14,M10<=$E$13),"-1",IF(M10=$E$13,0,IF(AND(M10>$E$13,M10<$E$12),1,IF(AND(M10>$E$12,M10<$E$11),2,IF(M10>$E$11,"3"))))))),"") | N11: =IFERROR(IF(N10<$E$16,"-3",IF(N10<$E$14,"-2",IF(AND(N10>=$E$14,N10<=$E$13),"-1",IF(N10=$E$13,0,IF(AND(N10>$E$13,N10<$E$12),1,IF(AND(N10>$E$12,N10<$E$11),2,IF(N10>$E$11,"3"))))))),"") | O11: =IFERROR(IF(O10<$E$16,"-3",IF(O10<$E$14,"-2",IF(AND(O10>=$E$14,O10<=$E$13),"-1",IF(O10=$E$13,0,IF(AND(O10>$E$13,O10<$E$12),1,IF(AND(O10>$E$12,O10<$E$11),2,IF(O10>$E$11,"3"))))))),"") | ... Q11: =IFERROR(IF(Q10<$E$16,"-3",IF(Q10<$E$14,"-2",IF(AND(Q10>=$E$14,Q10<=$E$13),"-1",IF(Q10=$E$13,0,IF(AND(Q10>$E$13,Q10<$E$12),1,IF(AND(Q10>$E$12,Q10<$E$11),2,IF(Q10>$E$11,"3"))))))),"") | T11: 3 | U11: Adjust the market size per country in row 8 in accordance with the scoring mechanism
B12: better than base | E12: 1.25 | T12: 4 | U12: Adjust the profit pool per country in row 13 per country according to the scoring adjustment
B13: same | E13: 1 | G13: Profit pool adjustment | H13: 1 | I13: 1 | J13: 1 | K13: 1 | L13: 1 | M13: 0 | N13: 0 | O13: 0 | P13: 0 | Q13: 0 | T13: 5 | U13: Determine the country attractiveness index (-3 - +3) in row 18
B14: worse than base | E14: 0.75 | G14: Profit pool '000 | H14: =$E$7*H6*H13 -> 0 | I14: =$E$7*I6*I13 -> 0 | J14: =$E$7*J6*J13 -> 0 | K14: =$E$7*K6*K13 -> 0 | L14: =$E$7*L6*L13 -> 0 | M14: =$E$7*M6*M13 -> 0 | N14: =$E$7*N6*N13 -> 0 | O14: =$E$7*O6*O13 -> 0 | ... Q14: =$E$7*Q6*Q13 -> 0 | R14: =AVERAGE(H14:Q14) -> 0
G15: average adjustment | H15: =(H14*100%)/$R$14 -> #DIV/0! | I15: =(I14*100%)/$R$14 -> #DIV/0! | J15: =(J14*100%)/$R$14 -> #DIV/0! | K15: =(K14*100%)/$R$14 -> #DIV/0! | L15: =(L14*100%)/$R$14 -> #DIV/0! | M15: =(M14*100%)/$R$14 -> #DIV/0! | N15: =(N14*100%)/$R$14 -> #DIV/0! | O15: =(O14*100%)/$R$14 -> #DIV/0! | ... Q15: =(Q14*100%)/$R$14 -> #DIV/0! | U15: row 19 automatically calculates the country attractiveness index
B16: much worse than base | E16: 0.5 | G16: profit size index (-3 to +3) | H16: =IFERROR(IF(H15<$E$16,"-3",IF(H15<$E$14,"-2",IF(AND(H15>=$E$14,H15<=$E$13),"-1",IF(H15=$E$13,0,IF(AND(H15>$E$13,H15<$E$12),1,IF(AND(H15>$E$12,H15<$E$11),2,IF(H15>$E$11,"3"))))))),"") | I16: =IFERROR(IF(I15<$E$16,"-3",IF(I15<$E$14,"-2",IF(AND(I15>=$E$14,I15<=$E$13),"-1",IF(I15=$E$13,0,IF(AND(I15>$E$13,I15<$E$12),1,IF(AND(I15>$E$12,I15<$E$11),2,IF(I15>$E$11,"3"))))))),"") | J16: =IFERROR(IF(J15<$E$16,"-3",IF(J15<$E$14,"-2",IF(AND(J15>=$E$14,J15<=$E$13),"-1",IF(J15=$E$13,0,IF(AND(J15>$E$13,J15<$E$12),1,IF(AND(J15>$E$12,J15<$E$11),2,IF(J15>$E$11,"3"))))))),"") | K16: =IFERROR(IF(K15<$E$16,"-3",IF(K15<$E$14,"-2",IF(AND(K15>=$E$14,K15<=$E$13),"-1",IF(K15=$E$13,0,IF(AND(K15>$E$13,K15<$E$12),1,IF(AND(K15>$E$12,K15<$E$11),2,IF(K15>$E$11,"3"))))))),"") | L16: =IFERROR(IF(L15<$E$16,"-3",IF(L15<$E$14,"-2",IF(AND(L15>=$E$14,L15<=$E$13),"-1",IF(L15=$E$13,0,IF(AND(L15>$E$13,L15<$E$12),1,IF(AND(L15>$E$12,L15<$E$11),2,IF(L15>$E$11,"3"))))))),"") | M16: =IFERROR(IF(M15<$E$16,"-3",IF(M15<$E$14,"-2",IF(AND(M15>=$E$14,M15<=$E$13),"-1",IF(M15=$E$13,0,IF(AND(M15>$E$13,M15<$E$12),1,IF(AND(M15>$E$12,M15<$E$11),2,IF(M15>$E$11,"3"))))))),"") | N16: =IFERROR(IF(N15<$E$16,"-3",IF(N15<$E$14,"-2",IF(AND(N15>=$E$14,N15<=$E$13),"-1",IF(N15=$E$13,0,IF(AND(N15>$E$13,N15<$E$12),1,IF(AND(N15>$E$12,N15<$E$11),2,IF(N15>$E$11,"3"))))))),"") | O16: =IFERROR(IF(O15<$E$16,"-3",IF(O15<$E$14,"-2",IF(AND(O15>=$E$14,O15<=$E$13),"-1",IF(O15=$E$13,0,IF(AND(O15>$E$13,O15<$E$12),1,IF(AND(O15>$E$12,O15<$E$11),2,IF(O15>$E$11,"3"))))))),"") | ... Q16: =IFERROR(IF(Q15<$E$16,"-3",IF(Q15<$E$14,"-2",IF(AND(Q15>=$E$14,Q15<=$E$13),"-1",IF(Q15=$E$13,0,IF(AND(Q15>$E$13,Q15<$E$12),1,IF(AND(Q15>$E$12,Q15<$E$11),2,IF(Q15>$E$11,"3"))))))),"") | U16: Final score is automatically calculated in row 20
B18: Country attractiveness adjustment | G18: country attractiveness | U18: Please only work on the BLUE cells
B19: very attractive | E19: 3
B20: attractive | E20: 2 | G20: Overall attractiveness index | H20: =IFERROR(H11+H16+H18,"") | I20: =IFERROR(I11+I16+I18,"") | J20: =IFERROR(J11+J16+J18,"") | K20: =IFERROR(K11+K16+K18,"") | L20: =IFERROR(L11+L16+L18,"") | M20: =IFERROR(M11+M16+M18,"") | N20: =IFERROR(N11+N16+N18,"") | O20: =IFERROR(O11+O16+O18,"") | ... Q20: =IFERROR(Q11+Q16+Q18,"")
B21: neutral | E21: 1
B22: not attractive | E22: -2
B23: very unattractive | E23: -3

Sheet Driving Forces brainstorm
F1: DRIVING FORCES ANALYSIS
F3: DRIVING FORCES BRAINSTORM | N3: TOP DIRIVING FORCES
C5: Rank | F5: WHY So the ability to predict the future is the ability to understand the driving forces. This tool will help you determine what are the forces in the environment that are going to have an impact on these numbers over the next three, four years. WHAT Identify and describe the main driving forces today that will determine the changes in your industry in the next 3 years. HOW 1. Create a list of the driving forces that are visible today. 2. Evaluate their potential impact on the industry • 1 - very low impact • 5 - very high impact 3. Evaluate the probability of occurence • 1 - very low probability • 5 - very high probability MISTAKES TO AVOID 1. Not having the top 3-5 driving forces with biggest impact. 2. Not understanding their impact on the industry. 3. Not eliminating the blind spots that hide some driving forces. 4. Not underestimate the speed and impact of technology. 5. Not interpret correctly the impact on consumer’s behaviour. | H5: List Driving Forces | I5: Impact (1-5) | J5: Probability (1-5) | K5: Score | N5: Top 10 Driving Forces
A7: =IF(H7<>"",COUNTIF($K7:K$7,K7),"") -> 1 | B7: =IF(H7<>"",IFERROR(RANK(K7,$K$7:$K$25,0),1),"") -> 1 | C7: =IF(ISNUMBER(B7),B7+A7-1,"") -> 1 | H7: Energy price increase | I7: 5 | J7: 3 | K7: =IF(H7<>"",(2*I7+J7),"") -> 13 | M7: 1 | N7: =IFERROR(INDEX($A$5:$J$1048576,MATCH($M7,$C$5:$C$25,0),MATCH($H$5,$5:$5,0)),"") -> Energy price increase
A8: =IF(H8<>"",COUNTIF($K$7:K8,K8),"") -> 1 | B8: =IF(H8<>"",IFERROR(RANK(K8,$K$7:$K$25,0),1),"") -> 7 | C8: =IF(ISNUMBER(B8),B8+A8-1,"") -> 7 | H8: Increase in the price of components | I8: 4 | J8: 3 | K8: =IF(H8<>"",(2*I8+J8),"") -> 11
A9: =IF(H9<>"",COUNTIF($K$7:K9,K9),"") -> 1 | B9: =IF(H9<>"",IFERROR(RANK(K9,$K$7:$K$25,0),1),"") -> 9 | C9: =IF(ISNUMBER(B9),B9+A9-1,"") -> 9 | H9: Launching subsidies and grants | I9: 3 | J9: 3 | K9: =IF(H9<>"",(2*I9+J9),"") -> 9
A10: =IF(H10<>"",COUNTIF($K$7:K10,K10),"") -> 2 | B10: =IF(H10<>"",IFERROR(RANK(K10,$K$7:$K$25,0),1),"") -> 1 | C10: =IF(ISNUMBER(B10),B10+A10-1,"") -> 2 | H10: Implement ESG in the commercial sector | I10: 4 | J10: 5 | K10: =IF(H10<>"",(2*I10+J10),"") -> 13 | M10: 2 | N10: =IFERROR(INDEX($A$5:$J$1048576,MATCH($M10,$C$5:$C$25,0),MATCH($H$5,$5:$5,0)),"") -> Implement ESG in the commercial sector
A11: =IF(H11<>"",COUNTIF($K$7:K11,K11),"") -> 1 | B11: =IF(H11<>"",IFERROR(RANK(K11,$K$7:$K$25,0),1),"") -> 3 | C11: =IF(ISNUMBER(B11),B11+A11-1,"") -> 3 | H11: Development of new products | I11: 4 | J11: 4 | K11: =IF(H11<>"",(2*I11+J11),"") -> 12 | M11: 3 | N11: =IFERROR(INDEX($A$5:$J$1048576,MATCH($M11,$C$5:$C$25,0),MATCH($H$5,$5:$5,0)),"") -> Development of new products
A12: =IF(H12<>"",COUNTIF($K$7:K12,K12),"") -> 2 | B12: =IF(H12<>"",IFERROR(RANK(K12,$K$7:$K$25,0),1),"") -> 9 | C12: =IF(ISNUMBER(B12),B12+A12-1,"") -> 10 | H12: Positive changes in legislation | I12: 3 | J12: 3 | K12: =IF(H12<>"",(2*I12+J12),"") -> 9 | M12: 4 | N12: =IFERROR(INDEX($A$5:$J$1048576,MATCH($M12,$C$5:$C$25,0),MATCH($H$5,$5:$5,0)),"") -> Increase in demand for electricity
A13: =IF(H13<>"",COUNTIF($K$7:K13,K13),"") -> 3 | B13: =IF(H13<>"",IFERROR(RANK(K13,$K$7:$K$25,0),1),"") -> 9 | C13: =IF(ISNUMBER(B13),B13+A13-1,"") -> 11 | H13: Customer awareness | I13: 3 | J13: 3 | K13: =IF(H13<>"",(2*I13+J13),"") -> 9 | M13: 5 | N13: =IFERROR(INDEX($A$5:$J$1048576,MATCH($M13,$C$5:$C$25,0),MATCH($H$5,$5:$5,0)),"") -> Development of new services
A14: =IF(H14<>"",COUNTIF($K$7:K14,K14),"") -> 1 | B14: =IF(H14<>"",IFERROR(RANK(K14,$K$7:$K$25,0),1),"") -> 15 | C14: =IF(ISNUMBER(B14),B14+A14-1,"") -> 15 | H14: Power grid conditions | I14: 3 | J14: 2 | K14: =IF(H14<>"",(2*I14+J14),"") -> 8 | M14: 6 | N14: =IFERROR(INDEX($A$5:$J$1048576,MATCH($M14,$C$5:$C$25,0),MATCH($H$5,$5:$5,0)),"") -> Cooperation with big 4
A15: =IF(H15<>"",COUNTIF($K$7:K15,K15),"") -> 4 | B15: =IF(H15<>"",IFERROR(RANK(K15,$K$7:$K$25,0),1),"") -> 9 | C15: =IF(ISNUMBER(B15),B15+A15-1,"") -> 12 | H15: Availability of qualified installers | I15: 3 | J15: 3 | K15: =IF(H15<>"",(2*I15+J15),"") -> 9 | M15: 7 | N15: =IFERROR(INDEX($A$5:$J$1048576,MATCH($M15,$C$5:$C$25,0),MATCH($H$5,$5:$5,0)),"") -> Increase in the price of components
A16: =IF(H16<>"",COUNTIF($K$7:K16,K16),"") -> 5 | B16: =IF(H16<>"",IFERROR(RANK(K16,$K$7:$K$25,0),1),"") -> 9 | C16: =IF(ISNUMBER(B16),B16+A16-1,"") -> 13 | H16: Availability of engineers and designers | I16: 3 | J16: 3 | K16: =IF(H16<>"",(2*I16+J16),"") -> 9
A17: =IF(H17<>"",COUNTIF($K$7:K17,K17),"") -> 2 | B17: =IF(H17<>"",IFERROR(RANK(K17,$K$7:$K$25,0),1),"") -> 7 | C17: =IF(ISNUMBER(B17),B17+A17-1,"") -> 8 | H17: Disproportion between hourly energy prices | I17: 4 | J17: 3 | K17: =IF(H17<>"",(2*I17+J17),"") -> 11
A18: =IF(H18<>"",COUNTIF($K$7:K18,K18),"") -> 2 | B18: =IF(H18<>"",IFERROR(RANK(K18,$K$7:$K$25,0),1),"") -> 15 | C18: =IF(ISNUMBER(B18),B18+A18-1,"") -> 16 | H18: Quality of components | I18: 2 | J18: 4 | K18: =IF(H18<>"",(2*I18+J18),"") -> 8
A19: =IF(H19<>"",COUNTIF($K$7:K19,K19),"") -> 2 | B19: =IF(H19<>"",IFERROR(RANK(K19,$K$7:$K$25,0),1),"") -> 3 | C19: =IF(ISNUMBER(B19),B19+A19-1,"") -> 4 | H19: Increase in demand for electricity | I19: 4 | J19: 4 | K19: =IF(H19<>"",(2*I19+J19),"") -> 12
A20: =IF(H20<>"",COUNTIF($K$7:K20,K20),"") -> 6 | B20: =IF(H20<>"",IFERROR(RANK(K20,$K$7:$K$25,0),1),"") -> 9 | C20: =IF(ISNUMBER(B20),B20+A20-1,"") -> 14 | H20: AI | I20: 3 | J20: 3 | K20: =IF(H20<>"",(2*I20+J20),"") -> 9
A21: =IF(H21<>"",COUNTIF($K$7:K21,K21),"") -> 3 | B21: =IF(H21<>"",IFERROR(RANK(K21,$K$7:$K$25,0),1),"") -> 3 | C21: =IF(ISNUMBER(B21),B21+A21-1,"") -> 5 | H21: Development of new services | I21: 4 | J21: 4 | K21: =IF(H21<>"",(2*I21+J21),"") -> 12
A22: =IF(H22<>"",COUNTIF($K$7:K22,K22),"") -> 4 | B22: =IF(H22<>"",IFERROR(RANK(K22,$K$7:$K$25,0),1),"") -> 3 | C22: =IF(ISNUMBER(B22),B22+A22-1,"") -> 6 | H22: Cooperation with big 4 | I22: 5 | J22: 2 | K22: =IF(H22<>"",(2*I22+J22),"") -> 12
A23: =IF(H23<>"",COUNTIF($K$7:K23,K23),"") | B23: =IF(H23<>"",IFERROR(RANK(K23,$K$7:$K$25,0),1),"") | C23: =IF(ISNUMBER(B23),B23+A23-1,"") | K23: =IF(H23<>"",(2*I23+J23),"") | N23: Back | O23: Market Size
A24: =IF(H24<>"",COUNTIF($K$7:K24,K24),"") | B24: =IF(H24<>"",IFERROR(RANK(K24,$K$7:$K$25,0),1),"") | C24: =IF(ISNUMBER(B24),B24+A24-1,"") | K24: =IF(H24<>"",(2*I24+J24),"")
A25: =IF(H25<>"",COUNTIF($K$7:K25,K25),"") | B25: =IF(H25<>"",IFERROR(RANK(K25,$K$7:$K$25,0),1),"") | C25: =IF(ISNUMBER(B25),B25+A25-1,"") | K25: =IF(H25<>"",(2*I25+J25),"") | N25: Next | O25: Driving Forces Impact

Sheet Driving Forces impact
C1: DRIVIGN FORCES IMPACT ANALYSIS
C3: DRIVING FORCES IMPACT
C5: WHY We are creating a strategy not for today, but for the next 3 years WHAT Understand how the market will change in the next years by estimating the effect of the driving forces on: 1. Number of clients 2. Their spending 3. Their number of purchases 4. Your gross profit margin HOW Understand what could be the impact of driving forces on: 1. Insert by what % amount (positive or negative) each driving force will change the four pillars (e.g. average spending will increase by 10%) | J5: ='Driving Forces brainstorm'!N7 -> Energy price increase | K5: ='Driving Forces brainstorm'!N10 -> Implement ESG in the commercial sector | L5: ='Driving Forces brainstorm'!N11 -> Development of new products | M5: ='Driving Forces brainstorm'!N12 -> Increase in demand for electricity | N5: ='Driving Forces brainstorm'!N13 -> Development of new services | O5: ='Driving Forces brainstorm'!N14 -> Cooperation with big 4 | P5: ='Driving Forces brainstorm'!N15 -> Increase in the price of components
E6: Total Number of Customers | J6: 0.15 | K6: 0.15 | L6: 0.25 | M6: 0 | N6: 0.25 | O6: 0.05 | P6: -0.05 | Q6: =(1+SUM(J6:P6))*'Market size'!K6 -> 237600
E7: Average Spending per Customer | J7: 0 | K7: 0 | L7: 0.3 | M7: 0 | N7: 0.3 | O7: 0 | P7: 0.25 | Q7: =(1+SUM(J7:P7))*'Market size'!K7 -> 1480000
E8: Average Number of Purchases per Year | J8: 0.1 | K8: 0.05 | L8: 0 | M8: 0 | N8: 0 | O8: 0 | P8: 0 | Q8: =(1+SUM(J8:P8))*'Market size'!K8 -> 0.0184
E9: Gross Profit Margin (%) | J9: 0 | K9: 0 | L9: 0.25 | M9: 0 | N9: 0.25 | O9: -0.25 | P9: 0 | Q9: =(1+SUM(J9:P9))*'Market size'!K9 -> 0.25
E11: Customers | F11: =YEAR(TODAY())+3 -> 2028 | H11: =Q6 -> 237600
E13: Market Size | F13: =YEAR(TODAY())+3 -> 2028 | H13: ='Market size'!I12*((1+SUM(J6:P6))*(1+SUM(J7:P7))*(1+SUM(J8:P8))) -> 6470323200 | N13: Back | O13: Driving Forces Brainstorm | Q13: =Q6*Q7*Q8 -> 6470323200
E15: Profit Pool | F15: =YEAR(TODAY())+3 -> 2028 | H15: =H13*'Market size'!K9*(1+SUM(J9:P9)) -> 1617580800 | N15: Next | O15: Segment Brainstorm | Q15: =Q13*Q9 -> 1617580800

Sheet Segment brainstorm
C1: MARKET SEGMENTATION
C3: Segmentation
E5: Needs brainstorm list | F5: Customer need clusters | G5: Potential segments | K5: The Core Industry Segments
C7: WHY Segmenting the customers by similar behaviors and needs is a CRITICAL step in the strategic process. This step is critical for the strategy development process and selecting your core customer. WHAT Segmentation is a tool that helps us to select a core consumer for whom to create a clear, focused, single-minded, and differentiated brand promise. HOW 1. Brainstorm different needs and behaviors of consumers of products and services in the industry. 2. In column E- try to identify clusters of customers according to shared needs and behaviors. 3. In column F- further narrow down the clusters until you define the industry's top 5-7 segments. These consumer groups need to be mutually exclusive and collectively exhaustive. MISTAKES TO AVOID 1. Thinking about the company's current customers - forget who you are and evaluate the segment groups in the entire industry. 2. Ending up with market segments (buckets) that are not covering all possible segments -e.g., they are not exhaustive. 3. Ending up with market segments (buckets) overlapping among each other- e.g., they are not mutually exclusive. | E7: Ograniczenie kosztów energii | F7: Ograniczenie kosztów energii | G7: Cały rynek | H7: {=IFERROR(INDEX($G$7:$G$490, MATCH(0,COUNTIF($H$6:H6, $G$7:$G$490), 0)),"")} -> Cały rynek | J7: 1 | K7: Gospodarstwa rolne
E8: Potrzeby ESG własne | F8: Potrzeby ESG | G8: Przedsiębiorstwa na taryfie C/B | H8: {=IFERROR(INDEX($G$7:$G$490, MATCH(0,COUNTIF($H$6:H7, $G$7:$G$490), 0)),"")} -> Przedsiębiorstwa na taryfie C/B | J8: 2
E9: Potrzeby ESG łańcucha dostaw | F9: Magazyny energii | G9: Cały rynek | H9: {=IFERROR(INDEX($G$7:$G$490, MATCH(0,COUNTIF($H$6:H8, $G$7:$G$490), 0)),"")} -> Przedsiębiorstwa | J9: 2 | K9: Gospodarstwa domowe
E10: Poprawa jakości sieci wewnętrznej | F10: Oferta kompleksowa 360 | G10: Cały rynek | H10: {=IFERROR(INDEX($G$7:$G$490, MATCH(0,COUNTIF($H$6:H9, $G$7:$G$490), 0)),"")} -> 0
E11: Backup - zasilanie awaryjne | F11: Elektromobilność | G11: Przedsiębiorstwa | H11: {=IFERROR(INDEX($G$7:$G$490, MATCH(0,COUNTIF($H$6:H10, $G$7:$G$490), 0)),"")} | J11: 3 | K11: Gminy/Samorządy
E12: Klient na usługę 360 - kompleksową | F12: Finansowanie | G12: Cały rynek | H12: {=IFERROR(INDEX($G$7:$G$490, MATCH(0,COUNTIF($H$6:H11, $G$7:$G$490), 0)),"")}
E13: Elektromobilność - 360 | F13: Regulacje | G13: Cały rynek | H13: {=IFERROR(INDEX($G$7:$G$490, MATCH(0,COUNTIF($H$6:H12, $G$7:$G$490), 0)),"")} | J13: 4 | K13: Obiekty na taryfie C
E14: Możliwości finansowania - dotacje | F14: Serwis | G14: Cały rynek | H14: {=IFERROR(INDEX($G$7:$G$490, MATCH(0,COUNTIF($H$6:H13, $G$7:$G$490), 0)),"")}
E15: Możliwości finansowania - SaaS | H15: {=IFERROR(INDEX($G$7:$G$490, MATCH(0,COUNTIF($H$6:H14, $G$7:$G$490), 0)),"")} | J15: 5 | K15: Obiekty na taryfie B
E16: Czas realizacji mała/duża instalacja | H16: {=IFERROR(INDEX($G$7:$G$490, MATCH(0,COUNTIF($H$6:H15, $G$7:$G$490), 0)),"")}
E17: Wizerunek | H17: {=IFERROR(INDEX($G$7:$G$490, MATCH(0,COUNTIF($H$6:H16, $G$7:$G$490), 0)),"")} | J17: 6 | K17: Farmy
E18: Trend | H18: {=IFERROR(INDEX($G$7:$G$490, MATCH(0,COUNTIF($H$6:H17, $G$7:$G$490), 0)),"")}
E19: Regulacje | H19: {=IFERROR(INDEX($G$7:$G$490, MATCH(0,COUNTIF($H$6:H18, $G$7:$G$490), 0)),"")} | J19: 7
E20: Serwis | H20: {=IFERROR(INDEX($G$7:$G$490, MATCH(0,COUNTIF($H$6:H19, $G$7:$G$490), 0)),"")}
H21: {=IFERROR(INDEX($G$7:$G$490, MATCH(0,COUNTIF($H$6:H20, $G$7:$G$490), 0)),"")} | J21: 8
H22: {=IFERROR(INDEX($G$7:$G$490, MATCH(0,COUNTIF($H$6:H21, $G$7:$G$490), 0)),"")}
H23: {=IFERROR(INDEX($G$7:$G$490, MATCH(0,COUNTIF($H$6:H22, $G$7:$G$490), 0)),"")}
H24: {=IFERROR(INDEX($G$7:$G$490, MATCH(0,COUNTIF($H$6:H23, $G$7:$G$490), 0)),"")} | K24: Back | L24: Driving Forces Impact
H25: {=IFERROR(INDEX($G$7:$G$490, MATCH(0,COUNTIF($H$6:H24, $G$7:$G$490), 0)),"")}
K26: Next | L26: Segment Quantification

Sheet Segment quantification
C1: CUSTOMER SEGMENTS QUANTIFICATION
C3: Segment Quantification
C5: WHAT The strategy development process is a combination between art and science and the ability to find a unique way to segment the market is the art part of strategy development. WHY A tool to help you quantify the segment. HOW 1. Calculate size and profitability of each segment as % of the market in 3 years MISTAKES TO AVOID Looking for data accuracy of more than 70%. Not having information for all segments. Looking for too much information. | E5: Quantify the Segments
G7: ='Segment brainstorm'!K7 -> Gospodarstwa rolne | H7: ='Segment brainstorm'!K9 -> Gospodarstwa domowe | I7: ='Segment brainstorm'!K11 -> Gminy/Samorządy | J7: ='Segment brainstorm'!K13 -> Obiekty na taryfie C | K7: ='Segment brainstorm'!K15 -> Obiekty na taryfie B | L7: ='Segment brainstorm'!K17 -> Farmy | M7: ='Segment brainstorm'!K19 -> 0 | N7: ='Segment brainstorm'!K21 -> 0 | O7: Total Check
E8: % of All Customers | G8: 0.15 | H8: 0.55 | I8: 0.05 | J8: 0.09 | K8: 0.01 | L8: 0.15 | O8: =SUM(G8:N8) -> 1
E9: % of Total Market Value | G9: 0.15 | H9: 0.55 | I9: 0.05 | J9: 0.09 | K9: 0.01 | L9: 0.15 | O9: =SUM(G9:N9) -> 1
E10: % of Total Profit Size | G10: 0.15 | H10: 0.55 | I10: 0.05 | J10: 0.09 | K10: 0.01 | L10: 0.15 | O10: =SUM(G10:N10) -> 1
E12: Segment Size
G14: =G7 -> Gospodarstwa rolne | H14: =H7 -> Gospodarstwa domowe | I14: =I7 -> Gminy/Samorządy | J14: =J7 -> Obiekty na taryfie C | K14: =K7 -> Obiekty na taryfie B | L14: =L7 -> Farmy | M14: =M7 -> 0 | N14: =N7 -> 0
E15: Number of Customers | G15: =G8*'Driving Forces impact'!$Q$6 -> 35640 | H15: =H8*'Driving Forces impact'!$Q$6 -> 130680 | I15: =I8*'Driving Forces impact'!$Q$6 -> 11880 | J15: =J8*'Driving Forces impact'!$Q$6 -> 21384 | K15: =K8*'Driving Forces impact'!$Q$6 -> 2376 | L15: =L8*'Driving Forces impact'!$Q$6 -> 35640 | M15: =M8*'Driving Forces impact'!$Q$6 -> 0 | N15: =N8*'Driving Forces impact'!$Q$6 -> 0
E16: Market size $$$ | G16: =G9*'Driving Forces impact'!$H$13 -> 970548480 | H16: =H9*'Driving Forces impact'!$H$13 -> 3.5586778e+09 | I16: =I9*'Driving Forces impact'!$H$13 -> 323516160 | J16: =J9*'Driving Forces impact'!$H$13 -> 582329088 | K16: =K9*'Driving Forces impact'!$H$13 -> 64703232 | L16: =L9*'Driving Forces impact'!$H$13 -> 970548480 | M16: =M9*'Driving Forces impact'!$H$13 -> 0 | N16: =N9*'Driving Forces impact'!$H$13 -> 0
E17: Profit Pool $$$ | G17: =G10*'Driving Forces impact'!$H$15 -> 242637120 | H17: =H10*'Driving Forces impact'!$H$15 -> 8.8966944e+08 | I17: =I10*'Driving Forces impact'!$H$15 -> 80879040 | J17: =J10*'Driving Forces impact'!$H$15 -> 145582272 | K17: =K10*'Driving Forces impact'!$H$15 -> 16175808 | L17: =L10*'Driving Forces impact'!$H$15 -> 242637120 | M17: =M10*'Driving Forces impact'!$H$15 -> 0 | N17: =N10*'Driving Forces impact'!$H$15 -> 0
K19: Back | L19: Segment Brainstorm
K21: Next | L21: Segment Ranking

Sheet Segment ranking
C1: CUSTOMER SEGMENTS RANKING
C3: Segment Ranking
C5: WHAT The strategy development process is a combination between art and science and the ability to find a unique way to segment the market is the art part of strategy development. WHY A tool to help you choose you target segment. HOW 1. Define weight for each segment ranking factor (from 1 to 5). Feel free to add one more factor. 2. Rank each segment on all factors (from 1 to 5): Size; Profitability; Trend (Is it going up or down?); Fit (How close is each segment to the current activities [products and services] that we offer today?) • 1 - very low • 5 - very high MISTAKES TO AVOID Not saying NO to as many segments as possible. Selected segments are not on a growth trajectory. Focusing only on the segments you currently know. | E5: Weight of each Pillar (1-5)
E6: Market Size | H6: 4
E7: Profit Pool | H7: 5
E8: Trend | H8: 4
E9: Fit with strategy | H9: 3
E12: Score of each Pillar per Segment (1-5)
E14: Segments | H14: ='Segment quantification'!G7 -> Gospodarstwa rolne | I14: ='Segment quantification'!H7 -> Gospodarstwa domowe | J14: ='Segment quantification'!I7 -> Gminy/Samorządy | K14: ='Segment quantification'!J7 -> Obiekty na taryfie C | L14: ='Segment quantification'!K7 -> Obiekty na taryfie B | M14: ='Segment quantification'!L7 -> Farmy | N14: ='Segment quantification'!M7 -> 0 | O14: ='Segment quantification'!N7 -> 0
E15: Market Size | H15: 2 | I15: 5 | J15: 2 | K15: 3 | L15: 1 | M15: 1
E16: Profit Pool | H16: 2 | I16: 2 | J16: 4 | K16: 3 | L16: 3 | M16: 2
E17: Trend | H17: 4 | I17: 2 | J17: 4 | K17: 3 | L17: 4 | M17: 1
E18: Fit with strategy | H18: 4 | I18: 2 | J18: 4 | K18: 4 | L18: 4 | M18: 1
E20: Sumproduct? | H20: =SUMPRODUCT($H$6:$H$10,H15:H19) -> 46 | I20: =SUMPRODUCT($H$6:$H$10,I15:I19) -> 44 | J20: =SUMPRODUCT($H$6:$H$10,J15:J19) -> 56 | K20: =SUMPRODUCT($H$6:$H$10,K15:K19) -> 51 | L20: =SUMPRODUCT($H$6:$H$10,L15:L19) -> 47 | M20: =SUMPRODUCT($H$6:$H$10,M15:M19) -> 21 | N20: =SUMPRODUCT($H$6:$H$10,N15:N19) -> 0 | O20: =SUMPRODUCT($H$6:$H$10,O15:O19) -> 0
E21: Repetative values? | H21: =COUNTIF($H20:H$20,H20) -> 1 | I21: =COUNTIF($H20:I$20,I20) -> 1 | J21: =COUNTIF($H20:J$20,J20) -> 1 | K21: =COUNTIF($H20:K$20,K20) -> 1 | L21: =COUNTIF($H20:L$20,L20) -> 1 | M21: =COUNTIF($H20:M$20,M20) -> 1 | N21: =COUNTIF($H20:N$20,N20) -> 1 | O21: =COUNTIF($H20:O$20,O20) -> 2
E22: Descending ranking? | H22: =RANK(H20,$H$20:$O$20,0) -> 4 | I22: =RANK(I20,$H$20:$O$20,0) -> 5 | J22: =RANK(J20,$H$20:$O$20,0) -> 1 | K22: =RANK(K20,$H$20:$O$20,0) -> 2 | L22: =RANK(L20,$H$20:$O$20,0) -> 3 | M22: =RANK(M20,$H$20:$O$20,0) -> 6 | N22: =RANK(N20,$H$20:$O$20,0) -> 7 | O22: =RANK(O20,$H$20:$O$20,0) -> 7
E23: Final ranking | H23: =H21+H22-1 -> 4 | I23: =I21+I22-1 -> 5 | J23: =J21+J22-1 -> 1 | K23: =K21+K22-1 -> 2 | L23: =L21+L22-1 -> 3 | M23: =M21+M22-1 -> 6 | N23: =N21+N22-1 -> 7 | O23: =O21+O22-1 -> 8
L26: Back | M26: Segment Quantification
L28: Next | M28: Segmentation Summary

Sheet Segment summary
C1: MARKET SUMMARY
C3: Market Summary
C5: Total Market | F5: =YEAR(TODAY()) -> 2025 | J5: REVIEW:
C7: Market Size | F7: ='Market size'!I12 -> 1689600000 | J7: Market Size
C9: Profit Pool | F9: ='Market size'!I14 -> 337920000 | J9: Driving Forces Brainstorm
C11: Number of Customers | F11: ='Market size'!K6 -> 132000 | J11: Driving Forces Impact
C13: Total Market | F13: =YEAR(TODAY())+3 -> 2028
C15: Market Size | F15: ='Driving Forces impact'!H13 -> 6470323200
C17: Profit Pool | F17: ='Driving Forces impact'!H15 -> 1617580800
C19: Number of Customers | F19: ='Driving Forces impact'!Q6 -> 237600
C21: Segment Summary
C23: Core Segment | F23: =INDEX('Segment ranking'!E12:O23, 3, MATCH(SMALL('Segment ranking'!H23:O23,1),'Segment ranking'!E23:O23,0)) -> Gminy/Samorządy | J23: REVIEW:
C25: Market Size | F25: =INDEX('Segment quantification'!$E$14:$N$17,3,MATCH('Segment summary'!F23,'Segment quantification'!$E$14:$N$14,0)) -> 323516160 | J25: Segment Brainstorm
C27: Profit Pool | F27: =INDEX('Segment quantification'!$E$14:$N$17,4,MATCH('Segment summary'!F23,'Segment quantification'!$E$14:$N$14,0)) -> 80879040 | J27: Segment Quantification
C29: Number of Customers | F29: =INDEX('Segment quantification'!$E$14:$N$17,2,MATCH('Segment summary'!F23,'Segment quantification'!$E$14:$N$14,0)) -> 11880 | J29: Segment Ranking
C31: Secondary Segment | F31: =INDEX('Segment ranking'!E12:O23, 3, MATCH(SMALL('Segment ranking'!H23:O23,2),'Segment ranking'!E23:O23,0)) -> Obiekty na taryfie C
C33: Market Size | F33: =INDEX('Segment quantification'!$E$14:$N$17,3,MATCH('Segment summary'!F31,'Segment quantification'!$E$14:$M$14,0)) -> 582329088
C35: Profit Pool | F35: =INDEX('Segment quantification'!$E$14:$N$17,4,MATCH('Segment summary'!F31,'Segment quantification'!$E$14:$M$14,0)) -> 145582272
C37: Number of Customers | F37: =INDEX('Segment quantification'!$E$14:$N$17,2,MATCH('Segment summary'!F31,'Segment quantification'!$E$14:$M$14,0)) -> 21384
C39: Total Target Segment Market
C41: Market Size | F41: =F33+F25 -> 905845248 | J41: REVIEW:
C43: Profit Pool | F43: =F35+F27 -> 226461312 | J43: Target Setting
C45: Number of Customers | F45: =F37+F29 -> 33264
C47: Total Target Summary
C49: 3-year Target
C51: Sales | F51: ='Target setting'!L19 -> 61468070
C53: Profit | F53: ='Target setting'!L21 -> 15367018
C55: 1-year Target | J55: Next Step
C57: Sales | F57: ='Target setting'!L25 -> 90584525 | J57: Segment Needs
C59: Profit | F59: ='Target setting'!L27 -> 22646131

Sheet Target setting
C1: TARGET SETTING
C3: Core and Secondary Target
I5: Core Segment | N5: Secondary Segment
C6: WHAT Determine the 3-5 year goals of the company on the basis of MARKET share and PROFIT POOL share. Target setting is a personal exercise and cannot be dictated by tools, formulas or consultants. HOW 1. Describe your CORE (and if applicable - also secondary) TARGET market. 2. Write down the size and profitability of your target segment in 3-5 years. 3. Set target market share and PROFIT target of the target segment. 4. Combine steps 2 and 3 to determine the overall size of the target market and the profit pool | F6: Target Segments | I6: ='Segment summary'!F23 -> Gminy/Samorządy | N6: ='Segment summary'!F31 -> Obiekty na taryfie C
F8: Market Size | I8: ='Segment summary'!F25 -> 323516160 | N8: ='Segment summary'!F33 -> 582329088
F9: Profit Pool | I9: ='Segment summary'!F27 -> 80879040 | N9: ='Segment summary'!F35 -> 145582272
F10: Customers | I10: ='Segment summary'!F29 -> 11880 | N10: ='Segment summary'!F37 -> 21384
F11: Average annual spending | I11: =IFERROR(I8/I10,"") -> 27232 | N11: =IFERROR(N8/N10,"") -> 27232
F14: Target Sales Share | I14: 0.1 | N14: 0.05
F15: Target Profit Share | I15: 0.1 | N15: 0.05
C18: WHAT Break down your 3 year goals into 1 year steps to make the achievement of the big goal easier. WHY A tool that helps you to define your 1 year goals HOW 1. Write down your 3 year goals 2. Break down the 3-year market share and profit share targets by defining what you would like to achieve next year 3. Define another 5 1-year targets that are aligned with your 3-year plan 4.Put numbers for each target | E18: 3-year target
F19: Total Sales Share Target | I19: =IFERROR(L19/'Segment summary'!F41,"") -> 0.067857143 | L19: ='Target setting'!I8*'Target setting'!I14+'Target setting'!N8*'Target setting'!N14 -> 61468070
F21: Total Profit Share Target | I21: =IFERROR(L21/'Segment summary'!F43,"") -> 0.067857143 | L21: ='Target setting'!I9*'Target setting'!I15+'Target setting'!N9*'Target setting'!N15 -> 15367018
E22: 1-year target
J23: [%] | Q23: [Number]
F25: Sales Share | I25: 0.1 | L25: =I25*(I8+N8) -> 90584525
F27: Profit Share | I27: 0.1 | L27: =I27*(I9+N9) -> 22646131
F29: Additional Target [text] | I29: Additional Target [value]
F31: Additional Target [text] | I31: Additional Target [value]
F33: Additional Target [text] | I33: Additional Target [value]
F35: Additional Target [text] | I35: Additional Target [value]
F37: Additional Target [text] | I37: Additional Target [value]
L39: Back | M39: Segment Ranking
L41: Next | M41: Core Segment Needs

Sheet Core segment needs
E2: Core customer Needs
E4: CORE SEGMENT NAME:… | G4: Describe the Segment
C7: Rank | E7: WHAT Develop an intimate understanding of the pains and needs that drive the behavior of our TARGET customers so we make their behavior PREDICTABLE WHY The foundation of setting up a customer-focused value proposition is a good understanding of needs and pains and how they are prioritized in the mind to the consumer HOW 1. Use the trigger questions at right to help you think of different potential customer needs: a. What is the one thing that your customer couldn’t live without accomplishing? b. What are the stepping stones that could help your customer achieve this key job? c. What are the different contexts that your customers might be in? How do their activities and goals change depending on these different contexts? d. What does your customer need to accomplish that involves interaction with others? e. Are there problems that you think customers have that they may not even be aware of? f. What emotional needs are your customers trying to satisfy? g. What jobs, if completed, would give the user a sense of selfsatisfaction? h. How does your customer want to be perceived by others? What can your customer do to help themselves be perceived this way? i. How does your customer want to feel? What does your customer need to do to feel this way? j. Track your customer’s interaction with a product or service throughout its lifespan. What supporting jobs surface throughout this life cycle? k. Does the user switch roles throughout this process? 2. Prioritize the needs according to how extreme they are in the customer’s eyes. Identify the top three needs of your core customer. | G7: List Segment Needs | H7: Importance (1-5) | I7: Size??? (1-5) | J7: Score | M7: Top Needs
A9: =IF(G9<>"",COUNTIF($J9:J$9,J9),"") | B9: =IF(G9<>"",IFERROR(RANK(J9,$J$9:$J$27,0),1),"") | C9: =IF(ISNUMBER(B9),B9+A9-1,"") | J9: =IF(G9<>"",(2*H9+I9),"") | L9: 1 | M9: =IFERROR(INDEX($A$7:$I$1048576,MATCH($L9,$C$7:$C$27,0),MATCH($G$7,$7:$7,0)),"")
A10: =IF(G10<>"",COUNTIF($J$9:J10,J10),"") | B10: =IF(G10<>"",IFERROR(RANK(J10,$J$9:$J$27,0),1),"") | C10: =IF(ISNUMBER(B10),B10+A10-1,"") | J10: =IF(G10<>"",(2*H10+I10),"") | L10: 2 | M10: =IFERROR(INDEX($A$7:$I$1048576,MATCH($L10,$C$7:$C$27,0),MATCH($G$7,$7:$7,0)),"")
A11: =IF(G11<>"",COUNTIF($J$9:J11,J11),"") | B11: =IF(G11<>"",IFERROR(RANK(J11,$J$9:$J$27,0),1),"") | C11: =IF(ISNUMBER(B11),B11+A11-1,"") | J11: =IF(G11<>"",(2*H11+I11),"") | L11: 3 | M11: =IFERROR(INDEX($A$7:$I$1048576,MATCH($L11,$C$7:$C$27,0),MATCH($G$7,$7:$7,0)),"")
A12: =IF(G12<>"",COUNTIF($J$9:J12,J12),"") | B12: =IF(G12<>"",IFERROR(RANK(J12,$J$9:$J$27,0),1),"") | C12: =IF(ISNUMBER(B12),B12+A12-1,"") | J12: =IF(G12<>"",(2*H12+I12),"")
A13: =IF(G13<>"",COUNTIF($J$9:J13,J13),"") | B13: =IF(G13<>"",IFERROR(RANK(J13,$J$9:$J$27,0),1),"") | C13: =IF(ISNUMBER(B13),B13+A13-1,"") | J13: =IF(G13<>"",(2*H13+I13),"") | L13: 4 | M13: =IFERROR(INDEX($A$7:$I$1048576,MATCH($L13,$C$7:$C$27,0),MATCH($G$7,$7:$7,0)),"")
A14: =IF(G14<>"",COUNTIF($J$9:J14,J14),"") | B14: =IF(G14<>"",IFERROR(RANK(J14,$J$9:$J$27,0),1),"") | C14: =IF(ISNUMBER(B14),B14+A14-1,"") | J14: =IF(G14<>"",(2*H14+I14),"") | L14: 5 | M14: =IFERROR(INDEX($A$7:$I$1048576,MATCH($L14,$C$7:$C$27,0),MATCH($G$7,$7:$7,0)),"")
A15: =IF(G15<>"",COUNTIF($J$9:J15,J15),"") | B15: =IF(G15<>"",IFERROR(RANK(J15,$J$9:$J$27,0),1),"") | C15: =IF(ISNUMBER(B15),B15+A15-1,"") | J15: =IF(G15<>"",(2*H15+I15),"") | L15: 6 | M15: =IFERROR(INDEX($A$7:$I$1048576,MATCH($L15,$C$7:$C$27,0),MATCH($G$7,$7:$7,0)),"")
A16: =IF(G16<>"",COUNTIF($J$9:J16,J16),"") | B16: =IF(G16<>"",IFERROR(RANK(J16,$J$9:$J$27,0),1),"") | C16: =IF(ISNUMBER(B16),B16+A16-1,"") | J16: =IF(G16<>"",(2*H16+I16),"") | L16: 7 | M16: =IFERROR(INDEX($A$7:$I$1048576,MATCH($L16,$C$7:$C$27,0),MATCH($G$7,$7:$7,0)),"")
A17: =IF(G17<>"",COUNTIF($J$9:J17,J17),"") | B17: =IF(G17<>"",IFERROR(RANK(J17,$J$9:$J$27,0),1),"") | C17: =IF(ISNUMBER(B17),B17+A17-1,"") | J17: =IF(G17<>"",(2*H17+I17),"") | L17: 8 | M17: =IFERROR(INDEX($A$7:$I$1048576,MATCH($L17,$C$7:$C$27,0),MATCH($G$7,$7:$7,0)),"")
A18: =IF(G18<>"",COUNTIF($J$9:J18,J18),"") | B18: =IF(G18<>"",IFERROR(RANK(J18,$J$9:$J$27,0),1),"") | C18: =IF(ISNUMBER(B18),B18+A18-1,"") | J18: =IF(G18<>"",(2*H18+I18),"") | L18: 9 | M18: =IFERROR(INDEX($A$7:$I$1048576,MATCH($L18,$C$7:$C$27,0),MATCH($G$7,$7:$7,0)),"")
A19: =IF(G19<>"",COUNTIF($J$9:J19,J19),"") | B19: =IF(G19<>"",IFERROR(RANK(J19,$J$9:$J$27,0),1),"") | C19: =IF(ISNUMBER(B19),B19+A19-1,"") | J19: =IF(G19<>"",(2*H19+I19),"") | L19: 10 | M19: =IFERROR(INDEX($A$7:$I$1048576,MATCH($L19,$C$7:$C$27,0),MATCH($G$7,$7:$7,0)),"")
A20: =IF(G20<>"",COUNTIF($J$9:J20,J20),"") | B20: =IF(G20<>"",IFERROR(RANK(J20,$J$9:$J$27,0),1),"") | C20: =IF(ISNUMBER(B20),B20+A20-1,"") | J20: =IF(G20<>"",(2*H20+I20),"")
A21: =IF(G21<>"",COUNTIF($J$9:J21,J21),"") | B21: =IF(G21<>"",IFERROR(RANK(J21,$J$9:$J$27,0),1),"") | C21: =IF(ISNUMBER(B21),B21+A21-1,"") | J21: =IF(G21<>"",(2*H21+I21),"")
A22: =IF(G22<>"",COUNTIF($J$9:J22,J22),"") | B22: =IF(G22<>"",IFERROR(RANK(J22,$J$9:$J$27,0),1),"") | C22: =IF(ISNUMBER(B22),B22+A22-1,"") | J22: =IF(G22<>"",(2*H22+I22),"")
A23: =IF(G23<>"",COUNTIF($J$9:J23,J23),"") | B23: =IF(G23<>"",IFERROR(RANK(J23,$J$9:$J$27,0),1),"") | C23: =IF(ISNUMBER(B23),B23+A23-1,"") | J23: =IF(G23<>"",(2*H23+I23),"")
A24: =IF(G24<>"",COUNTIF($J$9:J24,J24),"") | B24: =IF(G24<>"",IFERROR(RANK(J24,$J$9:$J$27,0),1),"") | C24: =IF(ISNUMBER(B24),B24+A24-1,"") | J24: =IF(G24<>"",(2*H24+I24),"")
A25: =IF(G25<>"",COUNTIF($J$9:J25,J25),"") | B25: =IF(G25<>"",IFERROR(RANK(J25,$J$9:$J$27,0),1),"") | C25: =IF(ISNUMBER(B25),B25+A25-1,"") | J25: =IF(G25<>"",(2*H25+I25),"") | M25: Back | N25: Segmentation Summary
A26: =IF(G26<>"",COUNTIF($J$9:J26,J26),"") | B26: =IF(G26<>"",IFERROR(RANK(J26,$J$9:$J$27,0),1),"") | C26: =IF(ISNUMBER(B26),B26+A26-1,"") | J26: =IF(G26<>"",(2*H26+I26),"")
A27: =IF(G27<>"",COUNTIF($J$9:J27,J27),"") | B27: =IF(G27<>"",IFERROR(RANK(J27,$J$9:$J$27,0),1),"") | C27: =IF(ISNUMBER(B27),B27+A27-1,"") | J27: =IF(G27<>"",(2*H27+I27),"") | M27: Next | N27: Secondary Segment Needs

Sheet Secondary segment needs
E2: Customer Needs
E4: SECONDARY SEGMENT NAME:… | G4: Describe the Segment
C7: Rank | E7: WHAT Develop an intimate understanding of the pains and needs that drive the behavior of our TARGET customers so we make their behavior PREDICTABLE WHY The foundation of setting up a customer-focused value proposition is a good understanding of needs and pains and how they are prioritized in the mind to the consumer HOW 1. Use the trigger questions at right to help you think of different potential customer needs: a. What is the one thing that your customer couldn’t live without accomplishing? b. What are the stepping stones that could help your customer achieve this key job? c. What are the different contexts that your customers might be in? How do their activities and goals change depending on these different contexts? d. What does your customer need to accomplish that involves interaction with others? e. Are there problems that you think customers have that they may not even be aware of? f. What emotional needs are your customers trying to satisfy? g. What jobs, if completed, would give the user a sense of self-satisfaction? h. How does your customer want to be perceived by others? What can your customer do to help themselves be perceived this way? i. How does your customer want to feel? What does your customer need to do to feel this way? j. Track your customer’s interaction with a product or service throughout its lifespan. What supporting jobs surface throughout this life cycle? k. Does the user switch roles throughout this process? 2. Prioritize the needs according to how extreme they are in the customer’s eyes. Identify the top three needs of your core customer. | G7: List Segment Needs | H7: Importance (1-5) | I7: Size??? (1-5) | J7: Score | M7: Top Needs
A9: =IF(G9<>"",COUNTIF($J9:J$9,J9),"") | B9: =IF(G9<>"",IFERROR(RANK(J9,$J$9:$J$27,0),1),"") | C9: =IF(ISNUMBER(B9),B9+A9-1,"") | J9: =IF(G9<>"",(2*H9+I9),"") | L9: 1 | M9: =IFERROR(INDEX($A$7:$I$1048576,MATCH($L9,$C$7:$C$27,0),MATCH($G$7,$7:$7,0)),"")
A10: =IF(G10<>"",COUNTIF($J$9:J10,J10),"") | B10: =IF(G10<>"",IFERROR(RANK(J10,$J$9:$J$27,0),1),"") | C10: =IF(ISNUMBER(B10),B10+A10-1,"") | J10: =IF(G10<>"",(2*H10+I10),"") | L10: 2 | M10: =IFERROR(INDEX($A$7:$I$1048576,MATCH($L10,$C$7:$C$27,0),MATCH($G$7,$7:$7,0)),"")
A11: =IF(G11<>"",COUNTIF($J$9:J11,J11),"") | B11: =IF(G11<>"",IFERROR(RANK(J11,$J$9:$J$27,0),1),"") | C11: =IF(ISNUMBER(B11),B11+A11-1,"") | J11: =IF(G11<>"",(2*H11+I11),"") | L11: 3 | M11: =IFERROR(INDEX($A$7:$I$1048576,MATCH($L11,$C$7:$C$27,0),MATCH($G$7,$7:$7,0)),"")
A12: =IF(G12<>"",COUNTIF($J$9:J12,J12),"") | B12: =IF(G12<>"",IFERROR(RANK(J12,$J$9:$J$27,0),1),"") | C12: =IF(ISNUMBER(B12),B12+A12-1,"") | J12: =IF(G12<>"",(2*H12+I12),"")
A13: =IF(G13<>"",COUNTIF($J$9:J13,J13),"") | B13: =IF(G13<>"",IFERROR(RANK(J13,$J$9:$J$27,0),1),"") | C13: =IF(ISNUMBER(B13),B13+A13-1,"") | J13: =IF(G13<>"",(2*H13+I13),"") | L13: 4 | M13: =IFERROR(INDEX($A$7:$I$1048576,MATCH($L13,$C$7:$C$27,0),MATCH($G$7,$7:$7,0)),"")
A14: =IF(G14<>"",COUNTIF($J$9:J14,J14),"") | B14: =IF(G14<>"",IFERROR(RANK(J14,$J$9:$J$27,0),1),"") | C14: =IF(ISNUMBER(B14),B14+A14-1,"") | J14: =IF(G14<>"",(2*H14+I14),"") | L14: 5 | M14: =IFERROR(INDEX($A$7:$I$1048576,MATCH($L14,$C$7:$C$27,0),MATCH($G$7,$7:$7,0)),"")
A15: =IF(G15<>"",COUNTIF($J$9:J15,J15),"") | B15: =IF(G15<>"",IFERROR(RANK(J15,$J$9:$J$27,0),1),"") | C15: =IF(ISNUMBER(B15),B15+A15-1,"") | J15: =IF(G15<>"",(2*H15+I15),"") | L15: 6 | M15: =IFERROR(INDEX($A$7:$I$1048576,MATCH($L15,$C$7:$C$27,0),MATCH($G$7,$7:$7,0)),"")
A16: =IF(G16<>"",COUNTIF($J$9:J16,J16),"") | B16: =IF(G16<>"",IFERROR(RANK(J16,$J$9:$J$27,0),1),"") | C16: =IF(ISNUMBER(B16),B16+A16-1,"") | J16: =IF(G16<>"",(2*H16+I16),"") | L16: 7 | M16: =IFERROR(INDEX($A$7:$I$1048576,MATCH($L16,$C$7:$C$27,0),MATCH($G$7,$7:$7,0)),"")
A17: =IF(G17<>"",COUNTIF($J$9:J17,J17),"") | B17: =IF(G17<>"",IFERROR(RANK(J17,$J$9:$J$27,0),1),"") | C17: =IF(ISNUMBER(B17),B17+A17-1,"") | J17: =IF(G17<>"",(2*H17+I17),"") | L17: 8 | M17: =IFERROR(INDEX($A$7:$I$1048576,MATCH($L17,$C$7:$C$27,0),MATCH($G$7,$7:$7,0)),"")
A18: =IF(G18<>"",COUNTIF($J$9:J18,J18),"") | B18: =IF(G18<>"",IFERROR(RANK(J18,$J$9:$J$27,0),1),"") | C18: =IF(ISNUMBER(B18),B18+A18-1,"") | J18: =IF(G18<>"",(2*H18+I18),"") | L18: 9 | M18: =IFERROR(INDEX($A$7:$I$1048576,MATCH($L18,$C$7:$C$27,0),MATCH($G$7,$7:$7,0)),"")
A19: =IF(G19<>"",COUNTIF($J$9:J19,J19),"") | B19: =IF(G19<>"",IFERROR(RANK(J19,$J$9:$J$27,0),1),"") | C19: =IF(ISNUMBER(B19),B19+A19-1,"") | J19: =IF(G19<>"",(2*H19+I19),"") | L19: 10 | M19: =IFERROR(INDEX($A$7:$I$1048576,MATCH($L19,$C$7:$C$27,0),MATCH($G$7,$7:$7,0)),"")
A20: =IF(G20<>"",COUNTIF($J$9:J20,J20),"") | B20: =IF(G20<>"",IFERROR(RANK(J20,$J$9:$J$27,0),1),"") | C20: =IF(ISNUMBER(B20),B20+A20-1,"") | J20: =IF(G20<>"",(2*H20+I20),"")
A21: =IF(G21<>"",COUNTIF($J$9:J21,J21),"") | B21: =IF(G21<>"",IFERROR(RANK(J21,$J$9:$J$27,0),1),"") | C21: =IF(ISNUMBER(B21),B21+A21-1,"") | J21: =IF(G21<>"",(2*H21+I21),"")
A22: =IF(G22<>"",COUNTIF($J$9:J22,J22),"") | B22: =IF(G22<>"",IFERROR(RANK(J22,$J$9:$J$27,0),1),"") | C22: =IF(ISNUMBER(B22),B22+A22-1,"") | J22: =IF(G22<>"",(2*H22+I22),"")
A23: =IF(G23<>"",COUNTIF($J$9:J23,J23),"") | B23: =IF(G23<>"",IFERROR(RANK(J23,$J$9:$J$27,0),1),"") | C23: =IF(ISNUMBER(B23),B23+A23-1,"") | J23: =IF(G23<>"",(2*H23+I23),"")
A24: =IF(G24<>"",COUNTIF($J$9:J24,J24),"") | B24: =IF(G24<>"",IFERROR(RANK(J24,$J$9:$J$27,0),1),"") | C24: =IF(ISNUMBER(B24),B24+A24-1,"") | J24: =IF(G24<>"",(2*H24+I24),"")
A25: =IF(G25<>"",COUNTIF($J$9:J25,J25),"") | B25: =IF(G25<>"",IFERROR(RANK(J25,$J$9:$J$27,0),1),"") | C25: =IF(ISNUMBER(B25),B25+A25-1,"") | J25: =IF(G25<>"",(2*H25+I25),"") | M25: Back | N25: Core Segment Needs
A26: =IF(G26<>"",COUNTIF($J$9:J26,J26),"") | B26: =IF(G26<>"",IFERROR(RANK(J26,$J$9:$J$27,0),1),"") | C26: =IF(ISNUMBER(B26),B26+A26-1,"") | J26: =IF(G26<>"",(2*H26+I26),"")
A27: =IF(G27<>"",COUNTIF($J$9:J27,J27),"") | B27: =IF(G27<>"",IFERROR(RANK(J27,$J$9:$J$27,0),1),"") | C27: =IF(ISNUMBER(B27),B27+A27-1,"") | J27: =IF(G27<>"",(2*H27+I27),"") | M27: Next | N27: Segment Needs Summary

Sheet Needs summary
B2: Core and Secondary Segment Needs Summary
B4: Core Segment Needs | H4: REVIEW:
D6: 1 | H6: Core Segment Needs
D8: 2
D10: 3
D12: 4
D14: 5
D16: 6
B18: Secondary Segment Needs | H18: REVIEW:
D20: 1 | H20: Secondary Segment Needs
D22: 2
D24: 3
D26: 4
D28: 5
D30: 6
