Workbook

Sheet Company Planning
D7: Company Annual Targets
C8: 1 | D8: MARKET SHARE (US si GR)
C9: 2 | D9: CASH (CCC)
C10: 3 | D10: EBIT
C11: 4 | D11: NET REVENUE (CAN)
C12: 5 | D12: B2C ACTIVE UNIQUE CUSTOMERS
C13: 6 | D13: SHARE GOOD ROUTINE (value & %)
C14: 7 | D14: SHARE OF A PLAYERS
D15: Company Annual priorities (big rocks) | K15: WHO | L15: KPI
C16: 1 | D16: Improve portfolio mix | K16: Tudor & Mada | L16: share vs immunity
C17: 2 | D17: JBPs with national chains | K17: Lucia / Paul | L17: net revenue
C18: 3 | D18: Consolidate RTM - launch Pediatric division, incentive, SIS, accelerator program, telesales, vizibilitate Secom in farmacii | K18: Lucia / Paul | L18: net revenue
C19: 4 | D19: Deploy digital sales channels | K19: Radu | L19: 10% of net online sales
C20: 5 | D20: Launch the new Retail concept | K20: Radu | L20: 1st of May
C21: 6 | D21: Improve execution of commercial calender - day by day, launch the new US campaign - de la scump la premium, commercial routines, launch brand etic corporate campaign | K21: Tudor & Mada | L21: 95% OTIF
C22: 7 | D22: Launch Good Routine Kids | K22: Mada | L22: Net revenue
C23: 8 | D23: Launch Good Routine Wellness Foods | K23: Andrei | L23: Portfolio
C24: 9 | D24: AI in business - discovering tools that can increase market share | K24: Johnny
C25: 10 | D25: Pilot in Modern Trade | K25: Paul
C26: 11 | D26: Digitalize/Automize top 5 processes - Forecast & Purchasing, Order to Cash, Reporting | K26: Johnny
C27: 12 | D27: Cost reduction program | K27: Adina
C28: 13 | D28: Talent Management program | K28: Andreia
C29: 14 | D29: Sustenabilitate | K29: Alina / Lucia | L29: 80% din Obiective
C30: 15 | D30: Logistics Excellence - TBD Idei | K30: George
C31: 16 | D31: Customer Centricity -> Share idei per Stakeholder (%) | K31: Alexandra / Adina | L31: 100 Idei Implementate
D33: Company Q1 targets
C34: 1 | D34: MARKET SHARE
C35: 2 | D35: CASH
C36: 3 | D36: EBIT
C37: 4 | D37: NET REVENUE
C38: 5 | D38: FINALIZE NEW RETAIL CONCEPT
C39: 6 | D39: MARKET SHARE GOOD ROUTINE vs SHARE GOOD ROUTINE (value & %)
C40: 7 | D40: FINALIZE TALENT MANAGEMENT CONCEPT & EVALUATION
D41: Company Q1 priorities (big rocks) | K41: WHO | L41: KPI
C42: 1 | K42: Department 1
C43: 2
C44: 3
C45: 4
C46: 5
C47: 6
C48: 7
D51: SAles | K51: Marketing US | R51: HR | Y51: GR | AF51: BT
C52: Q1 targets | J52: Q1 targets | Q52: Q1 targets | X52: Q1 targets | AE52: Q1 targets
C53: 1 | D53: Net Revenue US (CAN per Q) | J53: 1 | K53: Market Share US portfolio Q1 2025: 5.49% | Q53: 1 | R53: Talent Management process deployed | X53: 1 | Y53: Net Revenues (CAN) BU | AE53: 1 | AF53: Forecast Tool in BI
C54: 2 | D54: Net Revenue Good Routine | J54: 2 | K54: SOV TV Q1 pentru C, D3, CHLD: minim 10% | Q54: 2 | R54: Merit increase - keep in the budget | X54: 2 | Y54: Market Share & Share GR | AE54: 2 | AF54: SMART Reporting Automations (PBI / JetBI)
C55: 3 | D55: Distribution GR Kids & nonImmunity | J55: 3 | K55: CAN Childlife total brand: 8.195 K lei | Q55: 3 | R55: Recruit L&D | X55: 3 | Y55: Good Routine for Kids launch | AE55: 3 | AF55: Retail Customer Data Platform
C56: 4 | D56: DSO | J56: 4 | K56: CAN Prio 1.2.3 (Vit D3& Vit C adulti): 7.666 K lei | Q56: 4 | R56: Organize National Conference | X56: 4 | Y56: Commercial roadmap execution | AE56: 4 | AF56: Build AI squad in the company
C57: 5 | D57: Listing GR in Dr. Max & Catena | J57: 5 | K57: OTIF Social Media plans pentu US Q1 pentru brandurile din PRIO 1/2/3 | Q57: 5 | R57: Finish Performance management process for 2024 | X57: 5 | Y57: Contribution Margin (CM) BU | AE57: 5
C58: Q1 priorities | G58: WHO | H58: KPI | J58: Q1 priorities | N58: WHO | O58: KPI | Q58: Q1 priorities | U58: WHO | V58: KPI | X58: Q1 priorities | AB58: WHO | AC58: KPI | AE58: Q1 priorities | AI58: WHO | AJ58: KPI
C59: 1 | D59: Close JBPs with National Chains & Kas by 31.03 | G59: KAs | H59: OTIF | J59: 1 | K59: Shopper Childlife (Catena & Tei) | N59: Alexandra S | O59: OTIF | Q59: 1 | R59: Organize National Conference | U59: Doris | V59: In budget | X59: 1 | Y59: Execute commercial roadmap | AB59: Andreea N | AC59: OTIF | AE59: 1 | AF59: Setup BI data model (sources and input) for Baseline Forecast Implement predictive algorithm for Forecast in BI | AI59: M. Rizea | AJ59: OTIF
C60: 2 | D60: Define & start execute tools for DS: incentive, telesales, accelerator, cash collection | G60: Cristi | H60: OTIF | J60: 2 | K60: Shopper Secom Direct Imunitate | N60: Alexandra S | O60: OTIF | Q60: 2 | R60: Deploy Talent Management process & organize session for Managers of managers | U60: Andreia | V60: End of March | X60: 2 | Y60: Launch GR for Kids | AB60: Andreea N | AC60: OTIF | AE60: 2 | AF60: SMART Reporting - Analyze reporting process and needs across organization SMART Reporting - Develop report automations in JetBI or PBI | AI60: I. Burtea | AJ60: OTIF
C61: 3 | D61: Launch Pediatric Division in January | G61: Andreea | H61: OTIF | J61: 3 | K61: Campanie TV Childlife Q1 2025 | N61: Ruxandra S | O61: OTIF | Q61: 3 | R61: Analyse, propose & do Merit increase - 15 mar | U61: Doris | V61: In time & in budget | X61: 3 | AE61: 3 | AF61: Implement Customer Data Module in Klavyio Redesign Customer Data Processes (GDPR) for CDP | AI61: L. Boca | AJ61: OTIF
C62: 4 | D62: Define SEM role & activities | G62: Lucia / Paul | H62: OTIF | J62: 4 | K62: Distributie (sell in) CHLD non imunitate pentru pregatire Shopper Q2: Hepatocare, Allercare, Pure DHA, Cod liver Oil, Colostrum powder | N62: Alexandra S | O62: paritate distributie cu GR kids, pt activare in Q2 | Q62: 4 | R62: Finish Performance management process for 2024 | U62: Doris | V62: 20-Feb | X62: 4 | Y62: Prepare delivrables for Kids Shopper | AB62: Mihaela P | AC62: OTIF | AE62: 4 | AF62: Define AI Squad Objectives and Team | AI62: I. Burtea | AJ62: OTIF
C63: 5 | D63: Pilot Kaufland | G63: Diana | H63: OTIF | J63: 5 | K63: Team in full (incl. induction by end Q1) | N63: Tudor G | O63: 0 vacancies | Q63: 5 | R63: Recruit L&D | U63: Dina | V63: End of Jan | X63: 5 | Y63: Support and prepare Wellness Foods launch | AB63: Alexandra | AC63: OTIF | AE63: 5 | AF63: Priority 5

Sheet Department 1 - Q Planning
C1: DEPARTMENT 1 [NAME] QUARTERLY PLAN
D4: Department 1
C5: Q1 targets
C6: 1 | D6: Talent Management process deployed
C7: 2 | D7: Merit increase - keep in the budget
C8: 3 | D8: Recruit L&D
C9: 4 | D9: Organize National Conference
C10: 5 | D10: Finish Performance management process for 2024
C11: Q1 priorities | E11: WHO | F11: KPI
C12: 1 | D12: Organize National Conference | E12: Doris | F12: In budget
C13: 2 | D13: Deploy Talent Management process & organize session for Managers of managers | E13: Andreia | F13: End of March
C14: 3 | D14: Analyse, propose & do Merit increase - 15 mar | E14: Doris | F14: In time & in budget
C15: 4 | D15: Finish Performance management process for 2024 | E15: Doris | F15: 20-Feb
C16: 5 | D16: Recruit L&D | E16: Dina | F16: End of Jan
D19: Team member 1 (Name) | H19: Team member 2(Name) | L19: Team member 3 (Name) | P19: Team member 4 (Name) | T19: Team member 5 (Name) | X19: Team member 6 (Name)
C20: Q1 priorities | E20: KPI | G20: Q1 priorities | I20: KPI | K20: Q1 priorities | M20: KPI | O20: Q1 priorities | Q20: KPI | S20: Q1 priorities | U20: KPI | W20: Q1 priorities | Y20: KPI
C21: 1 | D21: Organize National Conference | E21: in the budget | G21: 1 | H21: Organize National Conference | I21: in the budget | K21: 1 | L21: Priority 1 | M21: % | O21: 1 | P21: Priority 1 | Q21: % | S21: 1 | T21: Priority 1 | U21: % | W21: 1 | X21: Priority 1 | Y21: %
C22: 2 | D22: Analyse, propose & do Merit increase - 15 mar | E22: End of March | G22: 2 | H22: Training Telesales Team | I22: Over 90% test score | K22: 2 | L22: Priority 2 | M22: % | O22: 2 | P22: Priority 2 | Q22: % | S22: 2 | T22: Priority 2 | U22: % | W22: 2 | X22: Priority 2 | Y22: %
C23: 3 | D23: Finish Performance management process for 2024 & Start & update Performance Management for 2025 | E23: End of Feb | G23: 3 | H23: Recruit L&D | I23: End of Jan | K23: 3 | L23: Priority 3 | M23: date | O23: 3 | P23: Priority 3 | Q23: date | S23: 3 | T23: Priority 3 | U23: # | W23: 3 | X23: Priority 3 | Y23: #
C24: 4 | D24: Priority 4 | E24: # | G24: 4 | H24: Priority 4 | I24: # | K24: 4 | L24: Priority 4 | M24: # | O24: 4 | P24: Priority 4 | Q24: # | S24: 4 | T24: Priority 4 | U24: # | W24: 4 | X24: Priority 4 | Y24: #
C25: 5 | D25: Priority 5 | E25: % | G25: 5 | H25: Priority 5 | I25: % | K25: 5 | L25: Priority 5 | M25: % | O25: 5 | P25: Priority 5 | Q25: % | S25: 5 | T25: Priority 5 | U25: % | W25: 5 | X25: Priority 5 | Y25: %

Sheet Department 1 - Week Performance
C1: DEPARTMENT 1 [NAME] WEEKLY AND DAILY PERFORMANCE
C4: ='Department 1 - Q Planning'!D19 -> Team member 1 (Name) | K4: =C4 -> Team member 1 (Name) | S4: =K4 -> Team member 1 (Name)
C5: Link to A | D5: # | E5: Q PRIORITIES | I5: KPI | K5: Link to A | L5: # | M5: Q PRIORITIES | Q5: KPI | S5: Link to A | T5: # | U5: Q PRIORITIES | Y5: KPI
D6: 1 | E6: ='Department 1 - Q Planning'!D21 -> Organize National Conference | I6: ='Department 1 - Q Planning'!E21 -> in the budget | L6: 1 | M6: =E6 -> Organize National Conference | Q6: =I6 -> in the budget | T6: 1 | U6: =M6 -> Organize National Conference | Y6: =Q6 -> in the budget
D7: 2 | E7: ='Department 1 - Q Planning'!D22 -> Analyse, propose & do Merit increase - 15 mar | I7: ='Department 1 - Q Planning'!E22 -> End of March | L7: 2 | M7: =E7 -> Analyse, propose & do Merit increase - 15 mar | Q7: =I7 -> End of March | T7: 2 | U7: =M7 -> Analyse, propose & do Merit increase - 15 mar | Y7: =Q7 -> End of March
D8: 3 | E8: ='Department 1 - Q Planning'!D23 -> Finish Performance management process for 2024 & Start & update Performance Management for 2025 | I8: ='Department 1 - Q Planning'!E23 -> End of Feb | L8: 3 | M8: =E8 -> Finish Performance management process for 2024 & Start & update Performance Management for 2025 | Q8: =I8 -> End of Feb | T8: 3 | U8: =M8 -> Finish Performance management process for 2024 & Start & update Performance Management for 2025 | Y8: =Q8 -> End of Feb
D9: 4 | E9: ='Department 1 - Q Planning'!D24 -> Priority 4 | I9: ='Department 1 - Q Planning'!E24 -> # | L9: 4 | M9: =E9 -> Priority 4 | Q9: =I9 -> # | T9: 4 | U9: =M9 -> Priority 4 | Y9: =Q9 -> #
D10: 5 | E10: ='Department 1 - Q Planning'!D25 -> Priority 5 | I10: ='Department 1 - Q Planning'!E25 -> % | L10: 5 | M10: =E10 -> Priority 5 | Q10: =I10 -> % | T10: 5 | U10: =M10 -> Priority 5 | Y10: =Q10 -> %
E11: WEEKLY PRIORITIES | M11: WEEKLY PRIORITIES | U11: WEEKLY PRIORITIES
C12: Link to Q | D12: # | E12: 47 | F12: DAY | G12: Completed? | H12: Reason if not completed | I12: WEEKLY LEARNING | K12: Link to Q | L12: # | M12: =E12+1 -> 48 | N12: DAY | O12: Completed? | P12: Reason if not completed | Q12: WEEKLY LEARNING | S12: Link to Q | T12: # | U12: =M12+1 -> 49 | V12: DAY | W12: Completed? | X12: Reason if not completed | Y12: WEEKLY LEARNING
D13: 1 | E13: Agree the presentation deck for Conference | F13: 1 | L13: 1 | T13: 1
D14: 2 | E14: List the Nominees for Awards | F14: 2 | L14: 2 | T14: 2
D15: 3 | E15: Confirm the participation list | F15: 3 | L15: 3 | T15: 3
D16: 4 | E16: Follow up with the Agency for the Conference activities | F16: 4 | L16: 4 | T16: 4
D17: 5 | E17: Create the Merit increase template and share the proposals with the BU directors | F17: 5 | L17: 5 | T17: 5
D18: 6 | L18: 6 | T18: 6
D19: Link to W | E19: DAILY PRIORITIES | F19: TIME | G19: Completed? | H19: Reason if not completed | I19: DAILY LEARNING | L19: Link to W | M19: DAILY PRIORITIES | N19: TIME | O19: Completed? | P19: Reason if not completed | Q19: DAILY LEARNING | T19: Link to W | U19: DAILY PRIORITIES | V19: TIME | W19: Completed? | X19: Reason if not completed | Y19: DAILY LEARNING
C20: M | E20: Share with Board members the contect and the template design for Conference | K20: M | S20: M
C23: T | K23: T | S23: T
C26: W | K26: W | S26: W
C29: T | K29: T | S29: T
C32: F | K32: F | S32: F
C37: ='Department 1 - Q Planning'!H19 -> Team member 2(Name) | K37: =C37 -> Team member 2(Name) | S37: =K37 -> Team member 2(Name)
C38: Link to A | D38: # | E38: Q PRIORITIES | I38: KPI | K38: Link to A | L38: # | M38: Q PRIORITIES | Q38: KPI | S38: Link to A | T38: # | U38: Q PRIORITIES | Y38: KPI
D39: 1 | E39: ='Department 1 - Q Planning'!H21 -> Organize National Conference | I39: ='Department 1 - Q Planning'!I21 -> in the budget | L39: 1 | M39: =E39 -> Organize National Conference | Q39: =I39 -> in the budget | T39: 1 | U39: =M39 -> Organize National Conference | Y39: =Q39 -> in the budget
D40: 2 | E40: ='Department 1 - Q Planning'!H22 -> Training Telesales Team | I40: ='Department 1 - Q Planning'!I22 -> Over 90% test score | L40: 2 | M40: =E40 -> Training Telesales Team | Q40: =I40 -> Over 90% test score | T40: 2 | U40: =M40 -> Training Telesales Team | Y40: =Q40 -> Over 90% test score
D41: 3 | E41: ='Department 1 - Q Planning'!H23 -> Recruit L&D | I41: ='Department 1 - Q Planning'!I23 -> End of Jan | L41: 3 | M41: =E41 -> Recruit L&D | Q41: =I41 -> End of Jan | T41: 3 | U41: =M41 -> Recruit L&D | Y41: =Q41 -> End of Jan
D42: 4 | E42: ='Department 1 - Q Planning'!H24 -> Priority 4 | I42: ='Department 1 - Q Planning'!I24 -> # | L42: 4 | M42: =E42 -> Priority 4 | Q42: =I42 -> # | T42: 4 | U42: =M42 -> Priority 4 | Y42: =Q42 -> #
D43: 5 | E43: ='Department 1 - Q Planning'!H25 -> Priority 5 | I43: ='Department 1 - Q Planning'!I25 -> % | L43: 5 | M43: =E43 -> Priority 5 | Q43: =I43 -> % | T43: 5 | U43: =M43 -> Priority 5 | Y43: =Q43 -> %
E44: WEEKLY PRIORITIES | M44: WEEKLY PRIORITIES | U44: WEEKLY PRIORITIES
C45: Link to Q | D45: # | E45: 47 | F45: DAY | G45: Completed? | H45: Reason if not completed | I45: WEEKLY LEARNING | K45: Link to Q | L45: # | M45: =E45+1 -> 48 | N45: DAY | O45: Completed? | P45: Reason if not completed | Q45: WEEKLY LEARNING | S45: Link to Q | T45: # | U45: =M45+1 -> 49 | V45: DAY | W45: Completed? | X45: Reason if not completed | Y45: WEEKLY LEARNING
D46: 1 | E46: Screening 50 cv's for L&D | L46: 1 | T46: 1
D47: 2 | E47: Select the best 10 and gave the short interview, propose min. 3. If not, screen again. | L47: 2 | T47: 2
D48: 3 | L48: 3 | T48: 3
D49: 4 | L49: 4 | T49: 4
D50: 5 | L50: 5 | T50: 5
D51: 6 | L51: 6 | T51: 6
D52: Link to W | E52: DAILY PRIORITIES | F52: TIME | G52: Completed? | H52: Reason if not completed | I52: DAILY LEARNING | L52: Link to W | M52: DAILY PRIORITIES | N52: TIME | O52: Completed? | P52: Reason if not completed | Q52: DAILY LEARNING | T52: Link to W | U52: DAILY PRIORITIES | V52: TIME | W52: Completed? | X52: Reason if not completed | Y52: DAILY LEARNING
C53: M | K53: M | S53: M
C56: T | K56: T | S56: T
C59: W | K59: W | S59: W
C62: T | K62: T | S62: T
C65: F | K65: F | S65: F
C70: ='Department 1 - Q Planning'!L19 -> Team member 3 (Name) | K70: =C70 -> Team member 3 (Name) | S70: =K70 -> Team member 3 (Name)
C71: Link to A | D71: # | E71: Q PRIORITIES | I71: KPI | K71: Link to A | L71: # | M71: Q PRIORITIES | Q71: KPI | S71: Link to A | T71: # | U71: Q PRIORITIES | Y71: KPI
D72: 1 | E72: ='Department 1 - Q Planning'!L21 -> Priority 1 | I72: ='Department 1 - Q Planning'!M21 -> % | L72: 1 | M72: =E72 -> Priority 1 | Q72: =I72 -> % | T72: 1 | U72: =M72 -> Priority 1 | Y72: =Q72 -> %
D73: 2 | E73: ='Department 1 - Q Planning'!L22 -> Priority 2 | I73: ='Department 1 - Q Planning'!M22 -> % | L73: 2 | M73: =E73 -> Priority 2 | Q73: =I73 -> % | T73: 2 | U73: =M73 -> Priority 2 | Y73: =Q73 -> %
D74: 3 | E74: ='Department 1 - Q Planning'!L23 -> Priority 3 | I74: ='Department 1 - Q Planning'!M23 -> date | L74: 3 | M74: =E74 -> Priority 3 | Q74: =I74 -> date | T74: 3 | U74: =M74 -> Priority 3 | Y74: =Q74 -> date
D75: 4 | E75: ='Department 1 - Q Planning'!L24 -> Priority 4 | I75: ='Department 1 - Q Planning'!M24 -> # | L75: 4 | M75: =E75 -> Priority 4 | Q75: =I75 -> # | T75: 4 | U75: =M75 -> Priority 4 | Y75: =Q75 -> #
D76: 5 | E76: ='Department 1 - Q Planning'!L25 -> Priority 5 | I76: ='Department 1 - Q Planning'!M25 -> % | L76: 5 | M76: =E76 -> Priority 5 | Q76: =I76 -> % | T76: 5 | U76: =M76 -> Priority 5 | Y76: =Q76 -> %
E77: WEEKLY PRIORITIES | M77: WEEKLY PRIORITIES | U77: WEEKLY PRIORITIES
C78: Link to Q | D78: # | E78: 47 | F78: DAY | G78: Completed? | H78: Reason if not completed | I78: WEEKLY LEARNING | K78: Link to Q | L78: # | M78: =E78+1 -> 48 | N78: DAY | O78: Completed? | P78: Reason if not completed | Q78: WEEKLY LEARNING | S78: Link to Q | T78: # | U78: =M78+1 -> 49 | V78: DAY | W78: Completed? | X78: Reason if not completed | Y78: WEEKLY LEARNING
D79: 1 | L79: 1 | T79: 1
D80: 2 | L80: 2 | T80: 2
D81: 3 | L81: 3 | T81: 3
D82: 4 | L82: 4 | T82: 4
D83: 5 | L83: 5 | T83: 5
D84: 6 | L84: 6 | T84: 6
D85: Link to W | E85: DAILY PRIORITIES | F85: TIME | G85: Completed? | H85: Reason if not completed | I85: DAILY LEARNING | L85: Link to W | M85: DAILY PRIORITIES | N85: TIME | O85: Completed? | P85: Reason if not completed | Q85: DAILY LEARNING | T85: Link to W | U85: DAILY PRIORITIES | V85: TIME | W85: Completed? | X85: Reason if not completed | Y85: DAILY LEARNING
C86: M | K86: M | S86: M
C89: T | K89: T | S89: T
C92: W | K92: W | S92: W
C95: T | K95: T | S95: T
C98: F | K98: F | S98: F
C103: ='Department 1 - Q Planning'!P19 -> Team member 4 (Name) | K103: =C103 -> Team member 4 (Name) | S103: =K103 -> Team member 4 (Name)
C104: Link to A | D104: # | E104: Q PRIORITIES | I104: KPI | K104: Link to A | L104: # | M104: Q PRIORITIES | Q104: KPI | S104: Link to A | T104: # | U104: Q PRIORITIES | Y104: KPI
D105: 1 | E105: ='Department 1 - Q Planning'!P21 -> Priority 1 | I105: ='Department 1 - Q Planning'!Q21 -> % | L105: 1 | M105: =E105 -> Priority 1 | Q105: =I105 -> % | T105: 1 | U105: =M105 -> Priority 1 | Y105: =Q105 -> %
D106: 2 | E106: ='Department 1 - Q Planning'!P22 -> Priority 2 | I106: ='Department 1 - Q Planning'!Q22 -> % | L106: 2 | M106: =E106 -> Priority 2 | Q106: =I106 -> % | T106: 2 | U106: =M106 -> Priority 2 | Y106: =Q106 -> %
D107: 3 | E107: ='Department 1 - Q Planning'!P23 -> Priority 3 | I107: ='Department 1 - Q Planning'!Q23 -> date | L107: 3 | M107: =E107 -> Priority 3 | Q107: =I107 -> date | T107: 3 | U107: =M107 -> Priority 3 | Y107: =Q107 -> date
D108: 4 | E108: ='Department 1 - Q Planning'!P24 -> Priority 4 | I108: ='Department 1 - Q Planning'!Q24 -> # | L108: 4 | M108: =E108 -> Priority 4 | Q108: =I108 -> # | T108: 4 | U108: =M108 -> Priority 4 | Y108: =Q108 -> #
D109: 5 | E109: ='Department 1 - Q Planning'!P25 -> Priority 5 | I109: ='Department 1 - Q Planning'!Q25 -> % | L109: 5 | M109: =E109 -> Priority 5 | Q109: =I109 -> % | T109: 5 | U109: =M109 -> Priority 5 | Y109: =Q109 -> %
E110: WEEKLY PRIORITIES | M110: WEEKLY PRIORITIES | U110: WEEKLY PRIORITIES
C111: Link to Q | D111: # | E111: 47 | F111: DAY | G111: Completed? | H111: Reason if not completed | I111: WEEKLY LEARNING | K111: Link to Q | L111: # | M111: =E111+1 -> 48 | N111: DAY | O111: Completed? | P111: Reason if not completed | Q111: WEEKLY LEARNING | S111: Link to Q | T111: # | U111: =M111+1 -> 49 | V111: DAY | W111: Completed? | X111: Reason if not completed | Y111: WEEKLY LEARNING
D112: 1 | L112: 1 | T112: 1
D113: 2 | L113: 2 | T113: 2
D114: 3 | L114: 3 | T114: 3
D115: 4 | L115: 4 | T115: 4
D116: 5 | L116: 5 | T116: 5
D117: 6 | L117: 6 | T117: 6
D118: Link to W | E118: DAILY PRIORITIES | F118: TIME | G118: Completed? | H118: Reason if not completed | I118: DAILY LEARNING | L118: Link to W | M118: DAILY PRIORITIES | N118: TIME | O118: Completed? | P118: Reason if not completed | Q118: DAILY LEARNING | T118: Link to W | U118: DAILY PRIORITIES | V118: TIME | W118: Completed? | X118: Reason if not completed | Y118: DAILY LEARNING
C119: M | K119: M | S119: M
C122: T | K122: T | S122: T
C125: W | K125: W | S125: W
C128: T | K128: T | S128: T
C131: F | K131: F | S131: F
C136: ='Department 1 - Q Planning'!T19 -> Team member 5 (Name) | K136: =C136 -> Team member 5 (Name) | S136: =K136 -> Team member 5 (Name)
C137: Link to A | D137: # | E137: Q PRIORITIES | I137: KPI | K137: Link to A | L137: # | M137: Q PRIORITIES | Q137: KPI | S137: Link to A | T137: # | U137: Q PRIORITIES | Y137: KPI
D138: 1 | E138: ='Department 1 - Q Planning'!T21 -> Priority 1 | I138: ='Department 1 - Q Planning'!U21 -> % | L138: 1 | M138: =E138 -> Priority 1 | Q138: =I138 -> % | T138: 1 | U138: =M138 -> Priority 1 | Y138: =Q138 -> %
D139: 2 | E139: ='Department 1 - Q Planning'!T22 -> Priority 2 | I139: ='Department 1 - Q Planning'!U22 -> % | L139: 2 | M139: =E139 -> Priority 2 | Q139: =I139 -> % | T139: 2 | U139: =M139 -> Priority 2 | Y139: =Q139 -> %
D140: 3 | E140: ='Department 1 - Q Planning'!T23 -> Priority 3 | I140: ='Department 1 - Q Planning'!U23 -> # | L140: 3 | M140: =E140 -> Priority 3 | Q140: =I140 -> # | T140: 3 | U140: =M140 -> Priority 3 | Y140: =Q140 -> #
D141: 4 | E141: ='Department 1 - Q Planning'!T24 -> Priority 4 | I141: ='Department 1 - Q Planning'!U24 -> # | L141: 4 | M141: =E141 -> Priority 4 | Q141: =I141 -> # | T141: 4 | U141: =M141 -> Priority 4 | Y141: =Q141 -> #
D142: 5 | E142: ='Department 1 - Q Planning'!T25 -> Priority 5 | I142: ='Department 1 - Q Planning'!U25 -> % | L142: 5 | M142: =E142 -> Priority 5 | Q142: =I142 -> % | T142: 5 | U142: =M142 -> Priority 5 | Y142: =Q142 -> %
E143: WEEKLY PRIORITIES | M143: WEEKLY PRIORITIES | U143: WEEKLY PRIORITIES
C144: Link to Q | D144: # | E144: 47 | F144: DAY | G144: Completed? | H144: Reason if not completed | I144: WEEKLY LEARNING | K144: Link to Q | L144: # | M144: =E144+1 -> 48 | N144: DAY | O144: Completed? | P144: Reason if not completed | Q144: WEEKLY LEARNING | S144: Link to Q | T144: # | U144: =M144+1 -> 49 | V144: DAY | W144: Completed? | X144: Reason if not completed | Y144: WEEKLY LEARNING
D145: 1 | L145: 1 | T145: 1
D146: 2 | L146: 2 | T146: 2
D147: 3 | L147: 3 | T147: 3
D148: 4 | L148: 4 | T148: 4
D149: 5 | L149: 5 | T149: 5
D150: 6 | L150: 6 | T150: 6
...

Sheet Dropdowns
B1: COMPLETION | D1: Reason if not completed
B2: Yes | D2: Bad scheduling
B3: No | D3: Not enough time
D4: Lack of capabilities
D5: Lack of resources
D6: No discipline
D7: Emergencies
